[{
		"identifier": "COMBOTS-aa4150-03e7",
		"edition": 999,
		"rank": 1
	},{
		"identifier": "COMBOTS-aa4150-03e6",
		"edition": 998,
		"rank": 2
	},{
		"identifier": "COMBOTS-aa4150-03e5",
		"edition": 997,
		"rank": 3
	},{
		"identifier": "COMBOTS-aa4150-03e4",
		"edition": 996,
		"rank": 4
	},{
		"identifier": "COMBOTS-aa4150-03e3",
		"edition": 995,
		"rank": 5
	},{
		"identifier": "COMBOTS-aa4150-03e2",
		"edition": 994,
		"rank": 6
	},{
		"identifier": "COMBOTS-aa4150-03e1",
		"edition": 993,
		"rank": 7
	},{
		"identifier": "COMBOTS-aa4150-03e0",
		"edition": 992,
		"rank": 8
	},{
		"identifier": "COMBOTS-aa4150-03df",
		"edition": 991,
		"rank": 9
	},{
		"identifier": "COMBOTS-aa4150-03de",
		"edition": 990,
		"rank": 10
	},{
		"identifier": "COMBOTS-aa4150-03dd",
		"edition": 989,
		"rank": 11
	},{
		"identifier": "COMBOTS-aa4150-03db",
		"edition": 987,
		"rank": 12
	},{
		"identifier": "COMBOTS-aa4150-0169",
		"edition": 361,
		"rank": 13
	},{
		"identifier": "COMBOTS-aa4150-02e8",
		"edition": 744,
		"rank": 14
	},{
		"identifier": "COMBOTS-aa4150-0108",
		"edition": 264,
		"rank": 15
	},{
		"identifier": "COMBOTS-aa4150-03c2",
		"edition": 962,
		"rank": 16
	},{
		"identifier": "COMBOTS-aa4150-02ce",
		"edition": 718,
		"rank": 17
	},{
		"identifier": "COMBOTS-aa4150-02c0",
		"edition": 704,
		"rank": 18
	},{
		"identifier": "COMBOTS-aa4150-e6",
		"edition": 230,
		"rank": 19
	},{
		"identifier": "COMBOTS-aa4150-03a5",
		"edition": 933,
		"rank": 20
	},{
		"identifier": "COMBOTS-aa4150-0385",
		"edition": 901,
		"rank": 21
	},{
		"identifier": "COMBOTS-aa4150-03a9",
		"edition": 937,
		"rank": 22
	},{
		"identifier": "COMBOTS-aa4150-df",
		"edition": 223,
		"rank": 23
	},{
		"identifier": "COMBOTS-aa4150-b2",
		"edition": 178,
		"rank": 24
	},{
		"identifier": "COMBOTS-aa4150-0165",
		"edition": 357,
		"rank": 25
	},{
		"identifier": "COMBOTS-aa4150-0393",
		"edition": 915,
		"rank": 26
	},{
		"identifier": "COMBOTS-aa4150-02e3",
		"edition": 739,
		"rank": 27
	},{
		"identifier": "COMBOTS-aa4150-79",
		"edition": 121,
		"rank": 28
	},{
		"identifier": "COMBOTS-aa4150-0395",
		"edition": 917,
		"rank": 29
	},{
		"identifier": "COMBOTS-aa4150-01a3",
		"edition": 419,
		"rank": 30
	},{
		"identifier": "COMBOTS-aa4150-0314",
		"edition": 788,
		"rank": 31
	},{
		"identifier": "COMBOTS-aa4150-0178",
		"edition": 376,
		"rank": 32
	},{
		"identifier": "COMBOTS-aa4150-034e",
		"edition": 846,
		"rank": 33
	},{
		"identifier": "COMBOTS-aa4150-6a",
		"edition": 106,
		"rank": 34
	},{
		"identifier": "COMBOTS-aa4150-02df",
		"edition": 735,
		"rank": 35
	},{
		"identifier": "COMBOTS-aa4150-02b6",
		"edition": 694,
		"rank": 36
	},{
		"identifier": "COMBOTS-aa4150-f9",
		"edition": 249,
		"rank": 37
	},{
		"identifier": "COMBOTS-aa4150-02d1",
		"edition": 721,
		"rank": 38
	},{
		"identifier": "COMBOTS-aa4150-026b",
		"edition": 619,
		"rank": 39
	},{
		"identifier": "COMBOTS-aa4150-e0",
		"edition": 224,
		"rank": 40
	},{
		"identifier": "COMBOTS-aa4150-018a",
		"edition": 394,
		"rank": 41
	},{
		"identifier": "COMBOTS-aa4150-0239",
		"edition": 569,
		"rank": 42
	},{
		"identifier": "COMBOTS-aa4150-03a6",
		"edition": 934,
		"rank": 43
	},{
		"identifier": "COMBOTS-aa4150-0121",
		"edition": 289,
		"rank": 44
	},{
		"identifier": "COMBOTS-aa4150-012f",
		"edition": 303,
		"rank": 45
	},{
		"identifier": "COMBOTS-aa4150-02d7",
		"edition": 727,
		"rank": 46
	},{
		"identifier": "COMBOTS-aa4150-69",
		"edition": 105,
		"rank": 47
	},{
		"identifier": "COMBOTS-aa4150-03ad",
		"edition": 941,
		"rank": 48
	},{
		"identifier": "COMBOTS-aa4150-4b",
		"edition": 75,
		"rank": 49
	},{
		"identifier": "COMBOTS-aa4150-14",
		"edition": 20,
		"rank": 50
	},{
		"identifier": "COMBOTS-aa4150-4a",
		"edition": 74,
		"rank": 51
	},{
		"identifier": "COMBOTS-aa4150-033f",
		"edition": 831,
		"rank": 52
	},{
		"identifier": "COMBOTS-aa4150-c5",
		"edition": 197,
		"rank": 53
	},{
		"identifier": "COMBOTS-aa4150-021a",
		"edition": 538,
		"rank": 54
	},{
		"identifier": "COMBOTS-aa4150-01ac",
		"edition": 428,
		"rank": 55
	},{
		"identifier": "COMBOTS-aa4150-035b",
		"edition": 859,
		"rank": 56
	},{
		"identifier": "COMBOTS-aa4150-ea",
		"edition": 234,
		"rank": 57
	},{
		"identifier": "COMBOTS-aa4150-010c",
		"edition": 268,
		"rank": 58
	},{
		"identifier": "COMBOTS-aa4150-010a",
		"edition": 266,
		"rank": 59
	},{
		"identifier": "COMBOTS-aa4150-020d",
		"edition": 525,
		"rank": 60
	},{
		"identifier": "COMBOTS-aa4150-96",
		"edition": 150,
		"rank": 61
	},{
		"identifier": "COMBOTS-aa4150-7e",
		"edition": 126,
		"rank": 62
	},{
		"identifier": "COMBOTS-aa4150-6b",
		"edition": 107,
		"rank": 63
	},{
		"identifier": "COMBOTS-aa4150-0214",
		"edition": 532,
		"rank": 64
	},{
		"identifier": "COMBOTS-aa4150-0324",
		"edition": 804,
		"rank": 65
	},{
		"identifier": "COMBOTS-aa4150-014b",
		"edition": 331,
		"rank": 66
	},{
		"identifier": "COMBOTS-aa4150-1b",
		"edition": 27,
		"rank": 67
	},{
		"identifier": "COMBOTS-aa4150-016b",
		"edition": 363,
		"rank": 68
	},{
		"identifier": "COMBOTS-aa4150-011b",
		"edition": 283,
		"rank": 69
	},{
		"identifier": "COMBOTS-aa4150-0330",
		"edition": 816,
		"rank": 70
	},{
		"identifier": "COMBOTS-aa4150-0208",
		"edition": 520,
		"rank": 71
	},{
		"identifier": "COMBOTS-aa4150-58",
		"edition": 88,
		"rank": 72
	},{
		"identifier": "COMBOTS-aa4150-01e7",
		"edition": 487,
		"rank": 73
	},{
		"identifier": "COMBOTS-aa4150-0205",
		"edition": 517,
		"rank": 74
	},{
		"identifier": "COMBOTS-aa4150-e3",
		"edition": 227,
		"rank": 75
	},{
		"identifier": "COMBOTS-aa4150-6e",
		"edition": 110,
		"rank": 76
	},{
		"identifier": "COMBOTS-aa4150-0150",
		"edition": 336,
		"rank": 77
	},{
		"identifier": "COMBOTS-aa4150-0243",
		"edition": 579,
		"rank": 78
	},{
		"identifier": "COMBOTS-aa4150-70",
		"edition": 112,
		"rank": 79
	},{
		"identifier": "COMBOTS-aa4150-02d6",
		"edition": 726,
		"rank": 80
	},{
		"identifier": "COMBOTS-aa4150-019f",
		"edition": 415,
		"rank": 81
	},{
		"identifier": "COMBOTS-aa4150-03c9",
		"edition": 969,
		"rank": 82
	},{
		"identifier": "COMBOTS-aa4150-93",
		"edition": 147,
		"rank": 83
	},{
		"identifier": "COMBOTS-aa4150-03bc",
		"edition": 956,
		"rank": 84
	},{
		"identifier": "COMBOTS-aa4150-0355",
		"edition": 853,
		"rank": 85
	},{
		"identifier": "COMBOTS-aa4150-76",
		"edition": 118,
		"rank": 86
	},{
		"identifier": "COMBOTS-aa4150-02eb",
		"edition": 747,
		"rank": 87
	},{
		"identifier": "COMBOTS-aa4150-013a",
		"edition": 314,
		"rank": 88
	},{
		"identifier": "COMBOTS-aa4150-034d",
		"edition": 845,
		"rank": 89
	},{
		"identifier": "COMBOTS-aa4150-5d",
		"edition": 93,
		"rank": 90
	},{
		"identifier": "COMBOTS-aa4150-01e1",
		"edition": 481,
		"rank": 91
	},{
		"identifier": "COMBOTS-aa4150-011a",
		"edition": 282,
		"rank": 92
	},{
		"identifier": "COMBOTS-aa4150-45",
		"edition": 69,
		"rank": 93
	},{
		"identifier": "COMBOTS-aa4150-01b7",
		"edition": 439,
		"rank": 94
	},{
		"identifier": "COMBOTS-aa4150-6c",
		"edition": 108,
		"rank": 95
	},{
		"identifier": "COMBOTS-aa4150-0253",
		"edition": 595,
		"rank": 96
	},{
		"identifier": "COMBOTS-aa4150-46",
		"edition": 70,
		"rank": 97
	},{
		"identifier": "COMBOTS-aa4150-0338",
		"edition": 824,
		"rank": 98
	},{
		"identifier": "COMBOTS-aa4150-0139",
		"edition": 313,
		"rank": 99
	},{
		"identifier": "COMBOTS-aa4150-0218",
		"edition": 536,
		"rank": 100
	},{
		"identifier": "COMBOTS-aa4150-0244",
		"edition": 580,
		"rank": 101
	},{
		"identifier": "COMBOTS-aa4150-02b2",
		"edition": 690,
		"rank": 102
	},{
		"identifier": "COMBOTS-aa4150-0303",
		"edition": 771,
		"rank": 103
	},{
		"identifier": "COMBOTS-aa4150-02e1",
		"edition": 737,
		"rank": 104
	},{
		"identifier": "COMBOTS-aa4150-030f",
		"edition": 783,
		"rank": 105
	},{
		"identifier": "COMBOTS-aa4150-c6",
		"edition": 198,
		"rank": 106
	},{
		"identifier": "COMBOTS-aa4150-01f5",
		"edition": 501,
		"rank": 107
	},{
		"identifier": "COMBOTS-aa4150-ed",
		"edition": 237,
		"rank": 108
	},{
		"identifier": "COMBOTS-aa4150-25",
		"edition": 37,
		"rank": 109
	},{
		"identifier": "COMBOTS-aa4150-017d",
		"edition": 381,
		"rank": 110
	},{
		"identifier": "COMBOTS-aa4150-021b",
		"edition": 539,
		"rank": 111
	},{
		"identifier": "COMBOTS-aa4150-0193",
		"edition": 403,
		"rank": 112
	},{
		"identifier": "COMBOTS-aa4150-022b",
		"edition": 555,
		"rank": 113
	},{
		"identifier": "COMBOTS-aa4150-027d",
		"edition": 637,
		"rank": 114
	},{
		"identifier": "COMBOTS-aa4150-0269",
		"edition": 617,
		"rank": 115
	},{
		"identifier": "COMBOTS-aa4150-037d",
		"edition": 893,
		"rank": 116
	},{
		"identifier": "COMBOTS-aa4150-ee",
		"edition": 238,
		"rank": 117
	},{
		"identifier": "COMBOTS-aa4150-72",
		"edition": 114,
		"rank": 118
	},{
		"identifier": "COMBOTS-aa4150-0207",
		"edition": 519,
		"rank": 119
	},{
		"identifier": "COMBOTS-aa4150-0250",
		"edition": 592,
		"rank": 120
	},{
		"identifier": "COMBOTS-aa4150-a4",
		"edition": 164,
		"rank": 121
	},{
		"identifier": "COMBOTS-aa4150-f4",
		"edition": 244,
		"rank": 122
	},{
		"identifier": "COMBOTS-aa4150-0249",
		"edition": 585,
		"rank": 123
	},{
		"identifier": "COMBOTS-aa4150-0168",
		"edition": 360,
		"rank": 124
	},{
		"identifier": "COMBOTS-aa4150-010b",
		"edition": 267,
		"rank": 125
	},{
		"identifier": "COMBOTS-aa4150-0319",
		"edition": 793,
		"rank": 126
	},{
		"identifier": "COMBOTS-aa4150-02c8",
		"edition": 712,
		"rank": 127
	},{
		"identifier": "COMBOTS-aa4150-03c5",
		"edition": 965,
		"rank": 128
	},{
		"identifier": "COMBOTS-aa4150-0146",
		"edition": 326,
		"rank": 129
	},{
		"identifier": "COMBOTS-aa4150-01bd",
		"edition": 445,
		"rank": 130
	},{
		"identifier": "COMBOTS-aa4150-5f",
		"edition": 95,
		"rank": 131
	},{
		"identifier": "COMBOTS-aa4150-013b",
		"edition": 315,
		"rank": 132
	},{
		"identifier": "COMBOTS-aa4150-02c7",
		"edition": 711,
		"rank": 133
	},{
		"identifier": "COMBOTS-aa4150-59",
		"edition": 89,
		"rank": 134
	},{
		"identifier": "COMBOTS-aa4150-027c",
		"edition": 636,
		"rank": 135
	},{
		"identifier": "COMBOTS-aa4150-01c1",
		"edition": 449,
		"rank": 136
	},{
		"identifier": "COMBOTS-aa4150-017a",
		"edition": 378,
		"rank": 137
	},{
		"identifier": "COMBOTS-aa4150-34",
		"edition": 52,
		"rank": 138
	},{
		"identifier": "COMBOTS-aa4150-01c8",
		"edition": 456,
		"rank": 139
	},{
		"identifier": "COMBOTS-aa4150-015e",
		"edition": 350,
		"rank": 140
	},{
		"identifier": "COMBOTS-aa4150-03a0",
		"edition": 928,
		"rank": 141
	},{
		"identifier": "COMBOTS-aa4150-8c",
		"edition": 140,
		"rank": 142
	},{
		"identifier": "COMBOTS-aa4150-f2",
		"edition": 242,
		"rank": 143
	},{
		"identifier": "COMBOTS-aa4150-0222",
		"edition": 546,
		"rank": 144
	},{
		"identifier": "COMBOTS-aa4150-75",
		"edition": 117,
		"rank": 145
	},{
		"identifier": "COMBOTS-aa4150-0166",
		"edition": 358,
		"rank": 146
	},{
		"identifier": "COMBOTS-aa4150-012b",
		"edition": 299,
		"rank": 147
	},{
		"identifier": "COMBOTS-aa4150-f8",
		"edition": 248,
		"rank": 148
	},{
		"identifier": "COMBOTS-aa4150-31",
		"edition": 49,
		"rank": 149
	},{
		"identifier": "COMBOTS-aa4150-03ae",
		"edition": 942,
		"rank": 150
	},{
		"identifier": "COMBOTS-aa4150-0332",
		"edition": 818,
		"rank": 151
	},{
		"identifier": "COMBOTS-aa4150-ec",
		"edition": 236,
		"rank": 152
	},{
		"identifier": "COMBOTS-aa4150-8e",
		"edition": 142,
		"rank": 153
	},{
		"identifier": "COMBOTS-aa4150-8f",
		"edition": 143,
		"rank": 154
	},{
		"identifier": "COMBOTS-aa4150-029c",
		"edition": 668,
		"rank": 155
	},{
		"identifier": "COMBOTS-aa4150-01da",
		"edition": 474,
		"rank": 156
	},{
		"identifier": "COMBOTS-aa4150-0368",
		"edition": 872,
		"rank": 157
	},{
		"identifier": "COMBOTS-aa4150-0212",
		"edition": 530,
		"rank": 158
	},{
		"identifier": "COMBOTS-aa4150-a0",
		"edition": 160,
		"rank": 159
	},{
		"identifier": "COMBOTS-aa4150-03b5",
		"edition": 949,
		"rank": 160
	},{
		"identifier": "COMBOTS-aa4150-0140",
		"edition": 320,
		"rank": 161
	},{
		"identifier": "COMBOTS-aa4150-0197",
		"edition": 407,
		"rank": 162
	},{
		"identifier": "COMBOTS-aa4150-73",
		"edition": 115,
		"rank": 163
	},{
		"identifier": "COMBOTS-aa4150-039e",
		"edition": 926,
		"rank": 164
	},{
		"identifier": "COMBOTS-aa4150-01ce",
		"edition": 462,
		"rank": 165
	},{
		"identifier": "COMBOTS-aa4150-6d",
		"edition": 109,
		"rank": 166
	},{
		"identifier": "COMBOTS-aa4150-028f",
		"edition": 655,
		"rank": 167
	},{
		"identifier": "COMBOTS-aa4150-026a",
		"edition": 618,
		"rank": 168
	},{
		"identifier": "COMBOTS-aa4150-037c",
		"edition": 892,
		"rank": 169
	},{
		"identifier": "COMBOTS-aa4150-02b0",
		"edition": 688,
		"rank": 170
	},{
		"identifier": "COMBOTS-aa4150-0271",
		"edition": 625,
		"rank": 171
	},{
		"identifier": "COMBOTS-aa4150-0155",
		"edition": 341,
		"rank": 172
	},{
		"identifier": "COMBOTS-aa4150-037a",
		"edition": 890,
		"rank": 173
	},{
		"identifier": "COMBOTS-aa4150-ef",
		"edition": 239,
		"rank": 174
	},{
		"identifier": "COMBOTS-aa4150-0233",
		"edition": 563,
		"rank": 175
	},{
		"identifier": "COMBOTS-aa4150-02c2",
		"edition": 706,
		"rank": 176
	},{
		"identifier": "COMBOTS-aa4150-0145",
		"edition": 325,
		"rank": 177
	},{
		"identifier": "COMBOTS-aa4150-03b8",
		"edition": 952,
		"rank": 178
	},{
		"identifier": "COMBOTS-aa4150-027b",
		"edition": 635,
		"rank": 179
	},{
		"identifier": "COMBOTS-aa4150-03b0",
		"edition": 944,
		"rank": 180
	},{
		"identifier": "COMBOTS-aa4150-02f4",
		"edition": 756,
		"rank": 181
	},{
		"identifier": "COMBOTS-aa4150-01cd",
		"edition": 461,
		"rank": 182
	},{
		"identifier": "COMBOTS-aa4150-02b9",
		"edition": 697,
		"rank": 183
	},{
		"identifier": "COMBOTS-aa4150-4c",
		"edition": 76,
		"rank": 184
	},{
		"identifier": "COMBOTS-aa4150-50",
		"edition": 80,
		"rank": 185
	},{
		"identifier": "COMBOTS-aa4150-0173",
		"edition": 371,
		"rank": 186
	},{
		"identifier": "COMBOTS-aa4150-02a2",
		"edition": 674,
		"rank": 187
	},{
		"identifier": "COMBOTS-aa4150-03c8",
		"edition": 968,
		"rank": 188
	},{
		"identifier": "COMBOTS-aa4150-02e2",
		"edition": 738,
		"rank": 189
	},{
		"identifier": "COMBOTS-aa4150-02c3",
		"edition": 707,
		"rank": 190
	},{
		"identifier": "COMBOTS-aa4150-0251",
		"edition": 593,
		"rank": 191
	},{
		"identifier": "COMBOTS-aa4150-9b",
		"edition": 155,
		"rank": 192
	},{
		"identifier": "COMBOTS-aa4150-02d2",
		"edition": 722,
		"rank": 193
	},{
		"identifier": "COMBOTS-aa4150-016e",
		"edition": 366,
		"rank": 194
	},{
		"identifier": "COMBOTS-aa4150-0321",
		"edition": 801,
		"rank": 195
	},{
		"identifier": "COMBOTS-aa4150-0367",
		"edition": 871,
		"rank": 196
	},{
		"identifier": "COMBOTS-aa4150-013e",
		"edition": 318,
		"rank": 197
	},{
		"identifier": "COMBOTS-aa4150-54",
		"edition": 84,
		"rank": 198
	},{
		"identifier": "COMBOTS-aa4150-01af",
		"edition": 431,
		"rank": 199
	},{
		"identifier": "COMBOTS-aa4150-01bf",
		"edition": 447,
		"rank": 200
	},{
		"identifier": "COMBOTS-aa4150-ae",
		"edition": 174,
		"rank": 201
	},{
		"identifier": "COMBOTS-aa4150-8b",
		"edition": 139,
		"rank": 202
	},{
		"identifier": "COMBOTS-aa4150-1f",
		"edition": 31,
		"rank": 203
	},{
		"identifier": "COMBOTS-aa4150-0181",
		"edition": 385,
		"rank": 204
	},{
		"identifier": "COMBOTS-aa4150-038a",
		"edition": 906,
		"rank": 205
	},{
		"identifier": "COMBOTS-aa4150-01d9",
		"edition": 473,
		"rank": 206
	},{
		"identifier": "COMBOTS-aa4150-0232",
		"edition": 562,
		"rank": 207
	},{
		"identifier": "COMBOTS-aa4150-0160",
		"edition": 352,
		"rank": 208
	},{
		"identifier": "COMBOTS-aa4150-0241",
		"edition": 577,
		"rank": 209
	},{
		"identifier": "COMBOTS-aa4150-e4",
		"edition": 228,
		"rank": 210
	},{
		"identifier": "COMBOTS-aa4150-9a",
		"edition": 154,
		"rank": 211
	},{
		"identifier": "COMBOTS-aa4150-d6",
		"edition": 214,
		"rank": 212
	},{
		"identifier": "COMBOTS-aa4150-e2",
		"edition": 226,
		"rank": 213
	},{
		"identifier": "COMBOTS-aa4150-01ea",
		"edition": 490,
		"rank": 214
	},{
		"identifier": "COMBOTS-aa4150-028e",
		"edition": 654,
		"rank": 215
	},{
		"identifier": "COMBOTS-aa4150-02c1",
		"edition": 705,
		"rank": 216
	},{
		"identifier": "COMBOTS-aa4150-c0",
		"edition": 192,
		"rank": 217
	},{
		"identifier": "COMBOTS-aa4150-03a7",
		"edition": 935,
		"rank": 218
	},{
		"identifier": "COMBOTS-aa4150-0225",
		"edition": 549,
		"rank": 219
	},{
		"identifier": "COMBOTS-aa4150-01b3",
		"edition": 435,
		"rank": 220
	},{
		"identifier": "COMBOTS-aa4150-0342",
		"edition": 834,
		"rank": 221
	},{
		"identifier": "COMBOTS-aa4150-36",
		"edition": 54,
		"rank": 222
	},{
		"identifier": "COMBOTS-aa4150-02f7",
		"edition": 759,
		"rank": 223
	},{
		"identifier": "COMBOTS-aa4150-9d",
		"edition": 157,
		"rank": 224
	},{
		"identifier": "COMBOTS-aa4150-07",
		"edition": 7,
		"rank": 225
	},{
		"identifier": "COMBOTS-aa4150-0133",
		"edition": 307,
		"rank": 226
	},{
		"identifier": "COMBOTS-aa4150-028d",
		"edition": 653,
		"rank": 227
	},{
		"identifier": "COMBOTS-aa4150-66",
		"edition": 102,
		"rank": 228
	},{
		"identifier": "COMBOTS-aa4150-014a",
		"edition": 330,
		"rank": 229
	},{
		"identifier": "COMBOTS-aa4150-02d4",
		"edition": 724,
		"rank": 230
	},{
		"identifier": "COMBOTS-aa4150-0131",
		"edition": 305,
		"rank": 231
	},{
		"identifier": "COMBOTS-aa4150-c4",
		"edition": 196,
		"rank": 232
	},{
		"identifier": "COMBOTS-aa4150-fb",
		"edition": 251,
		"rank": 233
	},{
		"identifier": "COMBOTS-aa4150-0174",
		"edition": 372,
		"rank": 234
	},{
		"identifier": "COMBOTS-aa4150-0117",
		"edition": 279,
		"rank": 235
	},{
		"identifier": "COMBOTS-aa4150-d2",
		"edition": 210,
		"rank": 236
	},{
		"identifier": "COMBOTS-aa4150-02aa",
		"edition": 682,
		"rank": 237
	},{
		"identifier": "COMBOTS-aa4150-01e9",
		"edition": 489,
		"rank": 238
	},{
		"identifier": "COMBOTS-aa4150-0328",
		"edition": 808,
		"rank": 239
	},{
		"identifier": "COMBOTS-aa4150-a1",
		"edition": 161,
		"rank": 240
	},{
		"identifier": "COMBOTS-aa4150-018f",
		"edition": 399,
		"rank": 241
	},{
		"identifier": "COMBOTS-aa4150-029f",
		"edition": 671,
		"rank": 242
	},{
		"identifier": "COMBOTS-aa4150-011f",
		"edition": 287,
		"rank": 243
	},{
		"identifier": "COMBOTS-aa4150-010f",
		"edition": 271,
		"rank": 244
	},{
		"identifier": "COMBOTS-aa4150-0339",
		"edition": 825,
		"rank": 245
	},{
		"identifier": "COMBOTS-aa4150-0163",
		"edition": 355,
		"rank": 246
	},{
		"identifier": "COMBOTS-aa4150-a3",
		"edition": 163,
		"rank": 247
	},{
		"identifier": "COMBOTS-aa4150-0176",
		"edition": 374,
		"rank": 248
	},{
		"identifier": "COMBOTS-aa4150-0206",
		"edition": 518,
		"rank": 249
	},{
		"identifier": "COMBOTS-aa4150-033a",
		"edition": 826,
		"rank": 250
	},{
		"identifier": "COMBOTS-aa4150-01f1",
		"edition": 497,
		"rank": 251
	},{
		"identifier": "COMBOTS-aa4150-0350",
		"edition": 848,
		"rank": 252
	},{
		"identifier": "COMBOTS-aa4150-02cc",
		"edition": 716,
		"rank": 253
	},{
		"identifier": "COMBOTS-aa4150-039f",
		"edition": 927,
		"rank": 254
	},{
		"identifier": "COMBOTS-aa4150-018c",
		"edition": 396,
		"rank": 255
	},{
		"identifier": "COMBOTS-aa4150-01fa",
		"edition": 506,
		"rank": 256
	},{
		"identifier": "COMBOTS-aa4150-0122",
		"edition": 290,
		"rank": 257
	},{
		"identifier": "COMBOTS-aa4150-024f",
		"edition": 591,
		"rank": 258
	},{
		"identifier": "COMBOTS-aa4150-019c",
		"edition": 412,
		"rank": 259
	},{
		"identifier": "COMBOTS-aa4150-0175",
		"edition": 373,
		"rank": 260
	},{
		"identifier": "COMBOTS-aa4150-23",
		"edition": 35,
		"rank": 261
	},{
		"identifier": "COMBOTS-aa4150-0191",
		"edition": 401,
		"rank": 262
	},{
		"identifier": "COMBOTS-aa4150-021c",
		"edition": 540,
		"rank": 263
	},{
		"identifier": "COMBOTS-aa4150-0348",
		"edition": 840,
		"rank": 264
	},{
		"identifier": "COMBOTS-aa4150-018e",
		"edition": 398,
		"rank": 265
	},{
		"identifier": "COMBOTS-aa4150-020f",
		"edition": 527,
		"rank": 266
	},{
		"identifier": "COMBOTS-aa4150-0d",
		"edition": 13,
		"rank": 267
	},{
		"identifier": "COMBOTS-aa4150-0307",
		"edition": 775,
		"rank": 268
	},{
		"identifier": "COMBOTS-aa4150-0263",
		"edition": 611,
		"rank": 269
	},{
		"identifier": "COMBOTS-aa4150-02bd",
		"edition": 701,
		"rank": 270
	},{
		"identifier": "COMBOTS-aa4150-02a0",
		"edition": 672,
		"rank": 271
	},{
		"identifier": "COMBOTS-aa4150-0220",
		"edition": 544,
		"rank": 272
	},{
		"identifier": "COMBOTS-aa4150-cf",
		"edition": 207,
		"rank": 273
	},{
		"identifier": "COMBOTS-aa4150-80",
		"edition": 128,
		"rank": 274
	},{
		"identifier": "COMBOTS-aa4150-015f",
		"edition": 351,
		"rank": 275
	},{
		"identifier": "COMBOTS-aa4150-0248",
		"edition": 584,
		"rank": 276
	},{
		"identifier": "COMBOTS-aa4150-01b6",
		"edition": 438,
		"rank": 277
	},{
		"identifier": "COMBOTS-aa4150-0356",
		"edition": 854,
		"rank": 278
	},{
		"identifier": "COMBOTS-aa4150-8d",
		"edition": 141,
		"rank": 279
	},{
		"identifier": "COMBOTS-aa4150-0274",
		"edition": 628,
		"rank": 280
	},{
		"identifier": "COMBOTS-aa4150-024b",
		"edition": 587,
		"rank": 281
	},{
		"identifier": "COMBOTS-aa4150-0371",
		"edition": 881,
		"rank": 282
	},{
		"identifier": "COMBOTS-aa4150-4e",
		"edition": 78,
		"rank": 283
	},{
		"identifier": "COMBOTS-aa4150-03b9",
		"edition": 953,
		"rank": 284
	},{
		"identifier": "COMBOTS-aa4150-0320",
		"edition": 800,
		"rank": 285
	},{
		"identifier": "COMBOTS-aa4150-0363",
		"edition": 867,
		"rank": 286
	},{
		"identifier": "COMBOTS-aa4150-038c",
		"edition": 908,
		"rank": 287
	},{
		"identifier": "COMBOTS-aa4150-02bc",
		"edition": 700,
		"rank": 288
	},{
		"identifier": "COMBOTS-aa4150-43",
		"edition": 67,
		"rank": 289
	},{
		"identifier": "COMBOTS-aa4150-02d8",
		"edition": 728,
		"rank": 290
	},{
		"identifier": "COMBOTS-aa4150-0106",
		"edition": 262,
		"rank": 291
	},{
		"identifier": "COMBOTS-aa4150-0389",
		"edition": 905,
		"rank": 292
	},{
		"identifier": "COMBOTS-aa4150-01d3",
		"edition": 467,
		"rank": 293
	},{
		"identifier": "COMBOTS-aa4150-0358",
		"edition": 856,
		"rank": 294
	},{
		"identifier": "COMBOTS-aa4150-029d",
		"edition": 669,
		"rank": 295
	},{
		"identifier": "COMBOTS-aa4150-1e",
		"edition": 30,
		"rank": 296
	},{
		"identifier": "COMBOTS-aa4150-0352",
		"edition": 850,
		"rank": 297
	},{
		"identifier": "COMBOTS-aa4150-98",
		"edition": 152,
		"rank": 298
	},{
		"identifier": "COMBOTS-aa4150-37",
		"edition": 55,
		"rank": 299
	},{
		"identifier": "COMBOTS-aa4150-019a",
		"edition": 410,
		"rank": 300
	},{
		"identifier": "COMBOTS-aa4150-011e",
		"edition": 286,
		"rank": 301
	},{
		"identifier": "COMBOTS-aa4150-017e",
		"edition": 382,
		"rank": 302
	},{
		"identifier": "COMBOTS-aa4150-028c",
		"edition": 652,
		"rank": 303
	},{
		"identifier": "COMBOTS-aa4150-0366",
		"edition": 870,
		"rank": 304
	},{
		"identifier": "COMBOTS-aa4150-0282",
		"edition": 642,
		"rank": 305
	},{
		"identifier": "COMBOTS-aa4150-012c",
		"edition": 300,
		"rank": 306
	},{
		"identifier": "COMBOTS-aa4150-01fd",
		"edition": 509,
		"rank": 307
	},{
		"identifier": "COMBOTS-aa4150-0159",
		"edition": 345,
		"rank": 308
	},{
		"identifier": "COMBOTS-aa4150-97",
		"edition": 151,
		"rank": 309
	},{
		"identifier": "COMBOTS-aa4150-0129",
		"edition": 297,
		"rank": 310
	},{
		"identifier": "COMBOTS-aa4150-023a",
		"edition": 570,
		"rank": 311
	},{
		"identifier": "COMBOTS-aa4150-0276",
		"edition": 630,
		"rank": 312
	},{
		"identifier": "COMBOTS-aa4150-0100",
		"edition": 256,
		"rank": 313
	},{
		"identifier": "COMBOTS-aa4150-03a4",
		"edition": 932,
		"rank": 314
	},{
		"identifier": "COMBOTS-aa4150-0209",
		"edition": 521,
		"rank": 315
	},{
		"identifier": "COMBOTS-aa4150-020e",
		"edition": 526,
		"rank": 316
	},{
		"identifier": "COMBOTS-aa4150-034b",
		"edition": 843,
		"rank": 317
	},{
		"identifier": "COMBOTS-aa4150-db",
		"edition": 219,
		"rank": 318
	},{
		"identifier": "COMBOTS-aa4150-0256",
		"edition": 598,
		"rank": 319
	},{
		"identifier": "COMBOTS-aa4150-0190",
		"edition": 400,
		"rank": 320
	},{
		"identifier": "COMBOTS-aa4150-0138",
		"edition": 312,
		"rank": 321
	},{
		"identifier": "COMBOTS-aa4150-036b",
		"edition": 875,
		"rank": 322
	},{
		"identifier": "COMBOTS-aa4150-5c",
		"edition": 92,
		"rank": 323
	},{
		"identifier": "COMBOTS-aa4150-024d",
		"edition": 589,
		"rank": 324
	},{
		"identifier": "COMBOTS-aa4150-01e3",
		"edition": 483,
		"rank": 325
	},{
		"identifier": "COMBOTS-aa4150-2b",
		"edition": 43,
		"rank": 326
	},{
		"identifier": "COMBOTS-aa4150-02cd",
		"edition": 717,
		"rank": 327
	},{
		"identifier": "COMBOTS-aa4150-91",
		"edition": 145,
		"rank": 328
	},{
		"identifier": "COMBOTS-aa4150-f5",
		"edition": 245,
		"rank": 329
	},{
		"identifier": "COMBOTS-aa4150-02c9",
		"edition": 713,
		"rank": 330
	},{
		"identifier": "COMBOTS-aa4150-01c4",
		"edition": 452,
		"rank": 331
	},{
		"identifier": "COMBOTS-aa4150-023c",
		"edition": 572,
		"rank": 332
	},{
		"identifier": "COMBOTS-aa4150-03d6",
		"edition": 982,
		"rank": 333
	},{
		"identifier": "COMBOTS-aa4150-01c2",
		"edition": 450,
		"rank": 334
	},{
		"identifier": "COMBOTS-aa4150-0369",
		"edition": 873,
		"rank": 335
	},{
		"identifier": "COMBOTS-aa4150-da",
		"edition": 218,
		"rank": 336
	},{
		"identifier": "COMBOTS-aa4150-0351",
		"edition": 849,
		"rank": 337
	},{
		"identifier": "COMBOTS-aa4150-030e",
		"edition": 782,
		"rank": 338
	},{
		"identifier": "COMBOTS-aa4150-026d",
		"edition": 621,
		"rank": 339
	},{
		"identifier": "COMBOTS-aa4150-024a",
		"edition": 586,
		"rank": 340
	},{
		"identifier": "COMBOTS-aa4150-01f6",
		"edition": 502,
		"rank": 341
	},{
		"identifier": "COMBOTS-aa4150-0398",
		"edition": 920,
		"rank": 342
	},{
		"identifier": "COMBOTS-aa4150-0293",
		"edition": 659,
		"rank": 343
	},{
		"identifier": "COMBOTS-aa4150-01a4",
		"edition": 420,
		"rank": 344
	},{
		"identifier": "COMBOTS-aa4150-0273",
		"edition": 627,
		"rank": 345
	},{
		"identifier": "COMBOTS-aa4150-4f",
		"edition": 79,
		"rank": 346
	},{
		"identifier": "COMBOTS-aa4150-b5",
		"edition": 181,
		"rank": 347
	},{
		"identifier": "COMBOTS-aa4150-017f",
		"edition": 383,
		"rank": 348
	},{
		"identifier": "COMBOTS-aa4150-94",
		"edition": 148,
		"rank": 349
	},{
		"identifier": "COMBOTS-aa4150-026e",
		"edition": 622,
		"rank": 350
	},{
		"identifier": "COMBOTS-aa4150-0344",
		"edition": 836,
		"rank": 351
	},{
		"identifier": "COMBOTS-aa4150-bc",
		"edition": 188,
		"rank": 352
	},{
		"identifier": "COMBOTS-aa4150-0198",
		"edition": 408,
		"rank": 353
	},{
		"identifier": "COMBOTS-aa4150-014d",
		"edition": 333,
		"rank": 354
	},{
		"identifier": "COMBOTS-aa4150-2d",
		"edition": 45,
		"rank": 355
	},{
		"identifier": "COMBOTS-aa4150-02d9",
		"edition": 729,
		"rank": 356
	},{
		"identifier": "COMBOTS-aa4150-019e",
		"edition": 414,
		"rank": 357
	},{
		"identifier": "COMBOTS-aa4150-01e4",
		"edition": 484,
		"rank": 358
	},{
		"identifier": "COMBOTS-aa4150-41",
		"edition": 65,
		"rank": 359
	},{
		"identifier": "COMBOTS-aa4150-21",
		"edition": 33,
		"rank": 360
	},{
		"identifier": "COMBOTS-aa4150-0185",
		"edition": 389,
		"rank": 361
	},{
		"identifier": "COMBOTS-aa4150-031f",
		"edition": 799,
		"rank": 362
	},{
		"identifier": "COMBOTS-aa4150-0266",
		"edition": 614,
		"rank": 363
	},{
		"identifier": "COMBOTS-aa4150-02fa",
		"edition": 762,
		"rank": 364
	},{
		"identifier": "COMBOTS-aa4150-cb",
		"edition": 203,
		"rank": 365
	},{
		"identifier": "COMBOTS-aa4150-025a",
		"edition": 602,
		"rank": 366
	},{
		"identifier": "COMBOTS-aa4150-0213",
		"edition": 531,
		"rank": 367
	},{
		"identifier": "COMBOTS-aa4150-027f",
		"edition": 639,
		"rank": 368
	},{
		"identifier": "COMBOTS-aa4150-0392",
		"edition": 914,
		"rank": 369
	},{
		"identifier": "COMBOTS-aa4150-0397",
		"edition": 919,
		"rank": 370
	},{
		"identifier": "COMBOTS-aa4150-0300",
		"edition": 768,
		"rank": 371
	},{
		"identifier": "COMBOTS-aa4150-0234",
		"edition": 564,
		"rank": 372
	},{
		"identifier": "COMBOTS-aa4150-0189",
		"edition": 393,
		"rank": 373
	},{
		"identifier": "COMBOTS-aa4150-02ea",
		"edition": 746,
		"rank": 374
	},{
		"identifier": "COMBOTS-aa4150-036f",
		"edition": 879,
		"rank": 375
	},{
		"identifier": "COMBOTS-aa4150-011d",
		"edition": 285,
		"rank": 376
	},{
		"identifier": "COMBOTS-aa4150-0252",
		"edition": 594,
		"rank": 377
	},{
		"identifier": "COMBOTS-aa4150-015b",
		"edition": 347,
		"rank": 378
	},{
		"identifier": "COMBOTS-aa4150-02b8",
		"edition": 696,
		"rank": 379
	},{
		"identifier": "COMBOTS-aa4150-02e5",
		"edition": 741,
		"rank": 380
	},{
		"identifier": "COMBOTS-aa4150-5b",
		"edition": 91,
		"rank": 381
	},{
		"identifier": "COMBOTS-aa4150-0354",
		"edition": 852,
		"rank": 382
	},{
		"identifier": "COMBOTS-aa4150-0161",
		"edition": 353,
		"rank": 383
	},{
		"identifier": "COMBOTS-aa4150-01dc",
		"edition": 476,
		"rank": 384
	},{
		"identifier": "COMBOTS-aa4150-0268",
		"edition": 616,
		"rank": 385
	},{
		"identifier": "COMBOTS-aa4150-0312",
		"edition": 786,
		"rank": 386
	},{
		"identifier": "COMBOTS-aa4150-0167",
		"edition": 359,
		"rank": 387
	},{
		"identifier": "COMBOTS-aa4150-01aa",
		"edition": 426,
		"rank": 388
	},{
		"identifier": "COMBOTS-aa4150-b3",
		"edition": 179,
		"rank": 389
	},{
		"identifier": "COMBOTS-aa4150-039b",
		"edition": 923,
		"rank": 390
	},{
		"identifier": "COMBOTS-aa4150-1c",
		"edition": 28,
		"rank": 391
	},{
		"identifier": "COMBOTS-aa4150-0285",
		"edition": 645,
		"rank": 392
	},{
		"identifier": "COMBOTS-aa4150-02ac",
		"edition": 684,
		"rank": 393
	},{
		"identifier": "COMBOTS-aa4150-03ab",
		"edition": 939,
		"rank": 394
	},{
		"identifier": "COMBOTS-aa4150-01d1",
		"edition": 465,
		"rank": 395
	},{
		"identifier": "COMBOTS-aa4150-02fe",
		"edition": 766,
		"rank": 396
	},{
		"identifier": "COMBOTS-aa4150-aa",
		"edition": 170,
		"rank": 397
	},{
		"identifier": "COMBOTS-aa4150-02e4",
		"edition": 740,
		"rank": 398
	},{
		"identifier": "COMBOTS-aa4150-03bd",
		"edition": 957,
		"rank": 399
	},{
		"identifier": "COMBOTS-aa4150-035d",
		"edition": 861,
		"rank": 400
	},{
		"identifier": "COMBOTS-aa4150-2a",
		"edition": 42,
		"rank": 401
	},{
		"identifier": "COMBOTS-aa4150-0364",
		"edition": 868,
		"rank": 402
	},{
		"identifier": "COMBOTS-aa4150-81",
		"edition": 129,
		"rank": 403
	},{
		"identifier": "COMBOTS-aa4150-d1",
		"edition": 209,
		"rank": 404
	},{
		"identifier": "COMBOTS-aa4150-018d",
		"edition": 397,
		"rank": 405
	},{
		"identifier": "COMBOTS-aa4150-032b",
		"edition": 811,
		"rank": 406
	},{
		"identifier": "COMBOTS-aa4150-02ad",
		"edition": 685,
		"rank": 407
	},{
		"identifier": "COMBOTS-aa4150-02ff",
		"edition": 767,
		"rank": 408
	},{
		"identifier": "COMBOTS-aa4150-0120",
		"edition": 288,
		"rank": 409
	},{
		"identifier": "COMBOTS-aa4150-03d9",
		"edition": 985,
		"rank": 410
	},{
		"identifier": "COMBOTS-aa4150-85",
		"edition": 133,
		"rank": 411
	},{
		"identifier": "COMBOTS-aa4150-03a2",
		"edition": 930,
		"rank": 412
	},{
		"identifier": "COMBOTS-aa4150-02e9",
		"edition": 745,
		"rank": 413
	},{
		"identifier": "COMBOTS-aa4150-b6",
		"edition": 182,
		"rank": 414
	},{
		"identifier": "COMBOTS-aa4150-0223",
		"edition": 547,
		"rank": 415
	},{
		"identifier": "COMBOTS-aa4150-04",
		"edition": 4,
		"rank": 416
	},{
		"identifier": "COMBOTS-aa4150-0291",
		"edition": 657,
		"rank": 417
	},{
		"identifier": "COMBOTS-aa4150-038e",
		"edition": 910,
		"rank": 418
	},{
		"identifier": "COMBOTS-aa4150-03a3",
		"edition": 931,
		"rank": 419
	},{
		"identifier": "COMBOTS-aa4150-0227",
		"edition": 551,
		"rank": 420
	},{
		"identifier": "COMBOTS-aa4150-0148",
		"edition": 328,
		"rank": 421
	},{
		"identifier": "COMBOTS-aa4150-012a",
		"edition": 298,
		"rank": 422
	},{
		"identifier": "COMBOTS-aa4150-7d",
		"edition": 125,
		"rank": 423
	},{
		"identifier": "COMBOTS-aa4150-0349",
		"edition": 841,
		"rank": 424
	},{
		"identifier": "COMBOTS-aa4150-0390",
		"edition": 912,
		"rank": 425
	},{
		"identifier": "COMBOTS-aa4150-02dd",
		"edition": 733,
		"rank": 426
	},{
		"identifier": "COMBOTS-aa4150-02ef",
		"edition": 751,
		"rank": 427
	},{
		"identifier": "COMBOTS-aa4150-0216",
		"edition": 534,
		"rank": 428
	},{
		"identifier": "COMBOTS-aa4150-031e",
		"edition": 798,
		"rank": 429
	},{
		"identifier": "COMBOTS-aa4150-0115",
		"edition": 277,
		"rank": 430
	},{
		"identifier": "COMBOTS-aa4150-0228",
		"edition": 552,
		"rank": 431
	},{
		"identifier": "COMBOTS-aa4150-01a9",
		"edition": 425,
		"rank": 432
	},{
		"identifier": "COMBOTS-aa4150-01d0",
		"edition": 464,
		"rank": 433
	},{
		"identifier": "COMBOTS-aa4150-02da",
		"edition": 730,
		"rank": 434
	},{
		"identifier": "COMBOTS-aa4150-0362",
		"edition": 866,
		"rank": 435
	},{
		"identifier": "COMBOTS-aa4150-03b1",
		"edition": 945,
		"rank": 436
	},{
		"identifier": "COMBOTS-aa4150-036e",
		"edition": 878,
		"rank": 437
	},{
		"identifier": "COMBOTS-aa4150-56",
		"edition": 86,
		"rank": 438
	},{
		"identifier": "COMBOTS-aa4150-0a",
		"edition": 10,
		"rank": 439
	},{
		"identifier": "COMBOTS-aa4150-0182",
		"edition": 386,
		"rank": 440
	},{
		"identifier": "COMBOTS-aa4150-0134",
		"edition": 308,
		"rank": 441
	},{
		"identifier": "COMBOTS-aa4150-02b3",
		"edition": 691,
		"rank": 442
	},{
		"identifier": "COMBOTS-aa4150-034c",
		"edition": 844,
		"rank": 443
	},{
		"identifier": "COMBOTS-aa4150-0341",
		"edition": 833,
		"rank": 444
	},{
		"identifier": "COMBOTS-aa4150-1d",
		"edition": 29,
		"rank": 445
	},{
		"identifier": "COMBOTS-aa4150-eb",
		"edition": 235,
		"rank": 446
	},{
		"identifier": "COMBOTS-aa4150-039a",
		"edition": 922,
		"rank": 447
	},{
		"identifier": "COMBOTS-aa4150-02fd",
		"edition": 765,
		"rank": 448
	},{
		"identifier": "COMBOTS-aa4150-de",
		"edition": 222,
		"rank": 449
	},{
		"identifier": "COMBOTS-aa4150-9c",
		"edition": 156,
		"rank": 450
	},{
		"identifier": "COMBOTS-aa4150-0317",
		"edition": 791,
		"rank": 451
	},{
		"identifier": "COMBOTS-aa4150-0164",
		"edition": 356,
		"rank": 452
	},{
		"identifier": "COMBOTS-aa4150-0394",
		"edition": 916,
		"rank": 453
	},{
		"identifier": "COMBOTS-aa4150-0383",
		"edition": 899,
		"rank": 454
	},{
		"identifier": "COMBOTS-aa4150-0337",
		"edition": 823,
		"rank": 455
	},{
		"identifier": "COMBOTS-aa4150-0187",
		"edition": 391,
		"rank": 456
	},{
		"identifier": "COMBOTS-aa4150-029a",
		"edition": 666,
		"rank": 457
	},{
		"identifier": "COMBOTS-aa4150-01f0",
		"edition": 496,
		"rank": 458
	},{
		"identifier": "COMBOTS-aa4150-02b5",
		"edition": 693,
		"rank": 459
	},{
		"identifier": "COMBOTS-aa4150-0376",
		"edition": 886,
		"rank": 460
	},{
		"identifier": "COMBOTS-aa4150-0237",
		"edition": 567,
		"rank": 461
	},{
		"identifier": "COMBOTS-aa4150-39",
		"edition": 57,
		"rank": 462
	},{
		"identifier": "COMBOTS-aa4150-0283",
		"edition": 643,
		"rank": 463
	},{
		"identifier": "COMBOTS-aa4150-019b",
		"edition": 411,
		"rank": 464
	},{
		"identifier": "COMBOTS-aa4150-0399",
		"edition": 921,
		"rank": 465
	},{
		"identifier": "COMBOTS-aa4150-d9",
		"edition": 217,
		"rank": 466
	},{
		"identifier": "COMBOTS-aa4150-3c",
		"edition": 60,
		"rank": 467
	},{
		"identifier": "COMBOTS-aa4150-030b",
		"edition": 779,
		"rank": 468
	},{
		"identifier": "COMBOTS-aa4150-03ac",
		"edition": 940,
		"rank": 469
	},{
		"identifier": "COMBOTS-aa4150-9e",
		"edition": 158,
		"rank": 470
	},{
		"identifier": "COMBOTS-aa4150-02a8",
		"edition": 680,
		"rank": 471
	},{
		"identifier": "COMBOTS-aa4150-51",
		"edition": 81,
		"rank": 472
	},{
		"identifier": "COMBOTS-aa4150-0316",
		"edition": 790,
		"rank": 473
	},{
		"identifier": "COMBOTS-aa4150-ab",
		"edition": 171,
		"rank": 474
	},{
		"identifier": "COMBOTS-aa4150-0110",
		"edition": 272,
		"rank": 475
	},{
		"identifier": "COMBOTS-aa4150-0375",
		"edition": 885,
		"rank": 476
	},{
		"identifier": "COMBOTS-aa4150-01a1",
		"edition": 417,
		"rank": 477
	},{
		"identifier": "COMBOTS-aa4150-02bb",
		"edition": 699,
		"rank": 478
	},{
		"identifier": "COMBOTS-aa4150-014f",
		"edition": 335,
		"rank": 479
	},{
		"identifier": "COMBOTS-aa4150-47",
		"edition": 71,
		"rank": 480
	},{
		"identifier": "COMBOTS-aa4150-0215",
		"edition": 533,
		"rank": 481
	},{
		"identifier": "COMBOTS-aa4150-0260",
		"edition": 608,
		"rank": 482
	},{
		"identifier": "COMBOTS-aa4150-0151",
		"edition": 337,
		"rank": 483
	},{
		"identifier": "COMBOTS-aa4150-52",
		"edition": 82,
		"rank": 484
	},{
		"identifier": "COMBOTS-aa4150-0f",
		"edition": 15,
		"rank": 485
	},{
		"identifier": "COMBOTS-aa4150-021e",
		"edition": 542,
		"rank": 486
	},{
		"identifier": "COMBOTS-aa4150-b1",
		"edition": 177,
		"rank": 487
	},{
		"identifier": "COMBOTS-aa4150-d4",
		"edition": 212,
		"rank": 488
	},{
		"identifier": "COMBOTS-aa4150-74",
		"edition": 116,
		"rank": 489
	},{
		"identifier": "COMBOTS-aa4150-6f",
		"edition": 111,
		"rank": 490
	},{
		"identifier": "COMBOTS-aa4150-fa",
		"edition": 250,
		"rank": 491
	},{
		"identifier": "COMBOTS-aa4150-0334",
		"edition": 820,
		"rank": 492
	},{
		"identifier": "COMBOTS-aa4150-0288",
		"edition": 648,
		"rank": 493
	},{
		"identifier": "COMBOTS-aa4150-d3",
		"edition": 211,
		"rank": 494
	},{
		"identifier": "COMBOTS-aa4150-0327",
		"edition": 807,
		"rank": 495
	},{
		"identifier": "COMBOTS-aa4150-02f5",
		"edition": 757,
		"rank": 496
	},{
		"identifier": "COMBOTS-aa4150-0135",
		"edition": 309,
		"rank": 497
	},{
		"identifier": "COMBOTS-aa4150-01d7",
		"edition": 471,
		"rank": 498
	},{
		"identifier": "COMBOTS-aa4150-22",
		"edition": 34,
		"rank": 499
	},{
		"identifier": "COMBOTS-aa4150-03b3",
		"edition": 947,
		"rank": 500
	},{
		"identifier": "COMBOTS-aa4150-01b5",
		"edition": 437,
		"rank": 501
	},{
		"identifier": "COMBOTS-aa4150-0158",
		"edition": 344,
		"rank": 502
	},{
		"identifier": "COMBOTS-aa4150-0275",
		"edition": 629,
		"rank": 503
	},{
		"identifier": "COMBOTS-aa4150-bf",
		"edition": 191,
		"rank": 504
	},{
		"identifier": "COMBOTS-aa4150-08",
		"edition": 8,
		"rank": 505
	},{
		"identifier": "COMBOTS-aa4150-030d",
		"edition": 781,
		"rank": 506
	},{
		"identifier": "COMBOTS-aa4150-03c3",
		"edition": 963,
		"rank": 507
	},{
		"identifier": "COMBOTS-aa4150-a7",
		"edition": 167,
		"rank": 508
	},{
		"identifier": "COMBOTS-aa4150-033e",
		"edition": 830,
		"rank": 509
	},{
		"identifier": "COMBOTS-aa4150-03b2",
		"edition": 946,
		"rank": 510
	},{
		"identifier": "COMBOTS-aa4150-60",
		"edition": 96,
		"rank": 511
	},{
		"identifier": "COMBOTS-aa4150-a9",
		"edition": 169,
		"rank": 512
	},{
		"identifier": "COMBOTS-aa4150-d0",
		"edition": 208,
		"rank": 513
	},{
		"identifier": "COMBOTS-aa4150-0302",
		"edition": 770,
		"rank": 514
	},{
		"identifier": "COMBOTS-aa4150-037b",
		"edition": 891,
		"rank": 515
	},{
		"identifier": "COMBOTS-aa4150-0104",
		"edition": 260,
		"rank": 516
	},{
		"identifier": "COMBOTS-aa4150-02ca",
		"edition": 714,
		"rank": 517
	},{
		"identifier": "COMBOTS-aa4150-15",
		"edition": 21,
		"rank": 518
	},{
		"identifier": "COMBOTS-aa4150-025b",
		"edition": 603,
		"rank": 519
	},{
		"identifier": "COMBOTS-aa4150-0217",
		"edition": 535,
		"rank": 520
	},{
		"identifier": "COMBOTS-aa4150-d8",
		"edition": 216,
		"rank": 521
	},{
		"identifier": "COMBOTS-aa4150-03be",
		"edition": 958,
		"rank": 522
	},{
		"identifier": "COMBOTS-aa4150-0386",
		"edition": 902,
		"rank": 523
	},{
		"identifier": "COMBOTS-aa4150-a8",
		"edition": 168,
		"rank": 524
	},{
		"identifier": "COMBOTS-aa4150-03b4",
		"edition": 948,
		"rank": 525
	},{
		"identifier": "COMBOTS-aa4150-0304",
		"edition": 772,
		"rank": 526
	},{
		"identifier": "COMBOTS-aa4150-0272",
		"edition": 626,
		"rank": 527
	},{
		"identifier": "COMBOTS-aa4150-0289",
		"edition": 649,
		"rank": 528
	},{
		"identifier": "COMBOTS-aa4150-0180",
		"edition": 384,
		"rank": 529
	},{
		"identifier": "COMBOTS-aa4150-01ec",
		"edition": 492,
		"rank": 530
	},{
		"identifier": "COMBOTS-aa4150-09",
		"edition": 9,
		"rank": 531
	},{
		"identifier": "COMBOTS-aa4150-01fb",
		"edition": 507,
		"rank": 532
	},{
		"identifier": "COMBOTS-aa4150-b8",
		"edition": 184,
		"rank": 533
	},{
		"identifier": "COMBOTS-aa4150-0247",
		"edition": 583,
		"rank": 534
	},{
		"identifier": "COMBOTS-aa4150-0245",
		"edition": 581,
		"rank": 535
	},{
		"identifier": "COMBOTS-aa4150-0381",
		"edition": 897,
		"rank": 536
	},{
		"identifier": "COMBOTS-aa4150-0116",
		"edition": 278,
		"rank": 537
	},{
		"identifier": "COMBOTS-aa4150-0326",
		"edition": 806,
		"rank": 538
	},{
		"identifier": "COMBOTS-aa4150-02ed",
		"edition": 749,
		"rank": 539
	},{
		"identifier": "COMBOTS-aa4150-0152",
		"edition": 338,
		"rank": 540
	},{
		"identifier": "COMBOTS-aa4150-02af",
		"edition": 687,
		"rank": 541
	},{
		"identifier": "COMBOTS-aa4150-0236",
		"edition": 566,
		"rank": 542
	},{
		"identifier": "COMBOTS-aa4150-f1",
		"edition": 241,
		"rank": 543
	},{
		"identifier": "COMBOTS-aa4150-01eb",
		"edition": 491,
		"rank": 544
	},{
		"identifier": "COMBOTS-aa4150-028a",
		"edition": 650,
		"rank": 545
	},{
		"identifier": "COMBOTS-aa4150-0162",
		"edition": 354,
		"rank": 546
	},{
		"identifier": "COMBOTS-aa4150-e1",
		"edition": 225,
		"rank": 547
	},{
		"identifier": "COMBOTS-aa4150-0142",
		"edition": 322,
		"rank": 548
	},{
		"identifier": "COMBOTS-aa4150-19",
		"edition": 25,
		"rank": 549
	},{
		"identifier": "COMBOTS-aa4150-015d",
		"edition": 349,
		"rank": 550
	},{
		"identifier": "COMBOTS-aa4150-0b",
		"edition": 11,
		"rank": 551
	},{
		"identifier": "COMBOTS-aa4150-3b",
		"edition": 59,
		"rank": 552
	},{
		"identifier": "COMBOTS-aa4150-b0",
		"edition": 176,
		"rank": 553
	},{
		"identifier": "COMBOTS-aa4150-0202",
		"edition": 514,
		"rank": 554
	},{
		"identifier": "COMBOTS-aa4150-036c",
		"edition": 876,
		"rank": 555
	},{
		"identifier": "COMBOTS-aa4150-26",
		"edition": 38,
		"rank": 556
	},{
		"identifier": "COMBOTS-aa4150-0343",
		"edition": 835,
		"rank": 557
	},{
		"identifier": "COMBOTS-aa4150-bd",
		"edition": 189,
		"rank": 558
	},{
		"identifier": "COMBOTS-aa4150-0112",
		"edition": 274,
		"rank": 559
	},{
		"identifier": "COMBOTS-aa4150-e7",
		"edition": 231,
		"rank": 560
	},{
		"identifier": "COMBOTS-aa4150-3a",
		"edition": 58,
		"rank": 561
	},{
		"identifier": "COMBOTS-aa4150-03c0",
		"edition": 960,
		"rank": 562
	},{
		"identifier": "COMBOTS-aa4150-8a",
		"edition": 138,
		"rank": 563
	},{
		"identifier": "COMBOTS-aa4150-032a",
		"edition": 810,
		"rank": 564
	},{
		"identifier": "COMBOTS-aa4150-cc",
		"edition": 204,
		"rank": 565
	},{
		"identifier": "COMBOTS-aa4150-0336",
		"edition": 822,
		"rank": 566
	},{
		"identifier": "COMBOTS-aa4150-5a",
		"edition": 90,
		"rank": 567
	},{
		"identifier": "COMBOTS-aa4150-024e",
		"edition": 590,
		"rank": 568
	},{
		"identifier": "COMBOTS-aa4150-dc",
		"edition": 220,
		"rank": 569
	},{
		"identifier": "COMBOTS-aa4150-0259",
		"edition": 601,
		"rank": 570
	},{
		"identifier": "COMBOTS-aa4150-01d8",
		"edition": 472,
		"rank": 571
	},{
		"identifier": "COMBOTS-aa4150-0123",
		"edition": 291,
		"rank": 572
	},{
		"identifier": "COMBOTS-aa4150-0384",
		"edition": 900,
		"rank": 573
	},{
		"identifier": "COMBOTS-aa4150-020a",
		"edition": 522,
		"rank": 574
	},{
		"identifier": "COMBOTS-aa4150-022d",
		"edition": 557,
		"rank": 575
	},{
		"identifier": "COMBOTS-aa4150-035f",
		"edition": 863,
		"rank": 576
	},{
		"identifier": "COMBOTS-aa4150-02bf",
		"edition": 703,
		"rank": 577
	},{
		"identifier": "COMBOTS-aa4150-ac",
		"edition": 172,
		"rank": 578
	},{
		"identifier": "COMBOTS-aa4150-02be",
		"edition": 702,
		"rank": 579
	},{
		"identifier": "COMBOTS-aa4150-0109",
		"edition": 265,
		"rank": 580
	},{
		"identifier": "COMBOTS-aa4150-02cb",
		"edition": 715,
		"rank": 581
	},{
		"identifier": "COMBOTS-aa4150-63",
		"edition": 99,
		"rank": 582
	},{
		"identifier": "COMBOTS-aa4150-82",
		"edition": 130,
		"rank": 583
	},{
		"identifier": "COMBOTS-aa4150-48",
		"edition": 72,
		"rank": 584
	},{
		"identifier": "COMBOTS-aa4150-0235",
		"edition": 565,
		"rank": 585
	},{
		"identifier": "COMBOTS-aa4150-03d0",
		"edition": 976,
		"rank": 586
	},{
		"identifier": "COMBOTS-aa4150-022c",
		"edition": 556,
		"rank": 587
	},{
		"identifier": "COMBOTS-aa4150-01c6",
		"edition": 454,
		"rank": 588
	},{
		"identifier": "COMBOTS-aa4150-68",
		"edition": 104,
		"rank": 589
	},{
		"identifier": "COMBOTS-aa4150-0136",
		"edition": 310,
		"rank": 590
	},{
		"identifier": "COMBOTS-aa4150-0153",
		"edition": 339,
		"rank": 591
	},{
		"identifier": "COMBOTS-aa4150-35",
		"edition": 53,
		"rank": 592
	},{
		"identifier": "COMBOTS-aa4150-01f9",
		"edition": 505,
		"rank": 593
	},{
		"identifier": "COMBOTS-aa4150-0279",
		"edition": 633,
		"rank": 594
	},{
		"identifier": "COMBOTS-aa4150-01f2",
		"edition": 498,
		"rank": 595
	},{
		"identifier": "COMBOTS-aa4150-0311",
		"edition": 785,
		"rank": 596
	},{
		"identifier": "COMBOTS-aa4150-0230",
		"edition": 560,
		"rank": 597
	},{
		"identifier": "COMBOTS-aa4150-0308",
		"edition": 776,
		"rank": 598
	},{
		"identifier": "COMBOTS-aa4150-022f",
		"edition": 559,
		"rank": 599
	},{
		"identifier": "COMBOTS-aa4150-0224",
		"edition": 548,
		"rank": 600
	},{
		"identifier": "COMBOTS-aa4150-0277",
		"edition": 631,
		"rank": 601
	},{
		"identifier": "COMBOTS-aa4150-0144",
		"edition": 324,
		"rank": 602
	},{
		"identifier": "COMBOTS-aa4150-02c6",
		"edition": 710,
		"rank": 603
	},{
		"identifier": "COMBOTS-aa4150-78",
		"edition": 120,
		"rank": 604
	},{
		"identifier": "COMBOTS-aa4150-02f2",
		"edition": 754,
		"rank": 605
	},{
		"identifier": "COMBOTS-aa4150-034a",
		"edition": 842,
		"rank": 606
	},{
		"identifier": "COMBOTS-aa4150-01d2",
		"edition": 466,
		"rank": 607
	},{
		"identifier": "COMBOTS-aa4150-035e",
		"edition": 862,
		"rank": 608
	},{
		"identifier": "COMBOTS-aa4150-fe",
		"edition": 254,
		"rank": 609
	},{
		"identifier": "COMBOTS-aa4150-3d",
		"edition": 61,
		"rank": 610
	},{
		"identifier": "COMBOTS-aa4150-022a",
		"edition": 554,
		"rank": 611
	},{
		"identifier": "COMBOTS-aa4150-03d8",
		"edition": 984,
		"rank": 612
	},{
		"identifier": "COMBOTS-aa4150-0374",
		"edition": 884,
		"rank": 613
	},{
		"identifier": "COMBOTS-aa4150-01ab",
		"edition": 427,
		"rank": 614
	},{
		"identifier": "COMBOTS-aa4150-0391",
		"edition": 913,
		"rank": 615
	},{
		"identifier": "COMBOTS-aa4150-032d",
		"edition": 813,
		"rank": 616
	},{
		"identifier": "COMBOTS-aa4150-0299",
		"edition": 665,
		"rank": 617
	},{
		"identifier": "COMBOTS-aa4150-0246",
		"edition": 582,
		"rank": 618
	},{
		"identifier": "COMBOTS-aa4150-03ce",
		"edition": 974,
		"rank": 619
	},{
		"identifier": "COMBOTS-aa4150-0292",
		"edition": 658,
		"rank": 620
	},{
		"identifier": "COMBOTS-aa4150-0255",
		"edition": 597,
		"rank": 621
	},{
		"identifier": "COMBOTS-aa4150-023d",
		"edition": 573,
		"rank": 622
	},{
		"identifier": "COMBOTS-aa4150-0103",
		"edition": 259,
		"rank": 623
	},{
		"identifier": "COMBOTS-aa4150-0378",
		"edition": 888,
		"rank": 624
	},{
		"identifier": "COMBOTS-aa4150-015a",
		"edition": 346,
		"rank": 625
	},{
		"identifier": "COMBOTS-aa4150-033c",
		"edition": 828,
		"rank": 626
	},{
		"identifier": "COMBOTS-aa4150-30",
		"edition": 48,
		"rank": 627
	},{
		"identifier": "COMBOTS-aa4150-01ff",
		"edition": 511,
		"rank": 628
	},{
		"identifier": "COMBOTS-aa4150-89",
		"edition": 137,
		"rank": 629
	},{
		"identifier": "COMBOTS-aa4150-0186",
		"edition": 390,
		"rank": 630
	},{
		"identifier": "COMBOTS-aa4150-0127",
		"edition": 295,
		"rank": 631
	},{
		"identifier": "COMBOTS-aa4150-0149",
		"edition": 329,
		"rank": 632
	},{
		"identifier": "COMBOTS-aa4150-02d3",
		"edition": 723,
		"rank": 633
	},{
		"identifier": "COMBOTS-aa4150-025f",
		"edition": 607,
		"rank": 634
	},{
		"identifier": "COMBOTS-aa4150-0380",
		"edition": 896,
		"rank": 635
	},{
		"identifier": "COMBOTS-aa4150-0201",
		"edition": 513,
		"rank": 636
	},{
		"identifier": "COMBOTS-aa4150-0188",
		"edition": 392,
		"rank": 637
	},{
		"identifier": "COMBOTS-aa4150-02dc",
		"edition": 732,
		"rank": 638
	},{
		"identifier": "COMBOTS-aa4150-017b",
		"edition": 379,
		"rank": 639
	},{
		"identifier": "COMBOTS-aa4150-023b",
		"edition": 571,
		"rank": 640
	},{
		"identifier": "COMBOTS-aa4150-e9",
		"edition": 233,
		"rank": 641
	},{
		"identifier": "COMBOTS-aa4150-016a",
		"edition": 362,
		"rank": 642
	},{
		"identifier": "COMBOTS-aa4150-02f8",
		"edition": 760,
		"rank": 643
	},{
		"identifier": "COMBOTS-aa4150-01ad",
		"edition": 429,
		"rank": 644
	},{
		"identifier": "COMBOTS-aa4150-02b1",
		"edition": 689,
		"rank": 645
	},{
		"identifier": "COMBOTS-aa4150-0280",
		"edition": 640,
		"rank": 646
	},{
		"identifier": "COMBOTS-aa4150-42",
		"edition": 66,
		"rank": 647
	},{
		"identifier": "COMBOTS-aa4150-027e",
		"edition": 638,
		"rank": 648
	},{
		"identifier": "COMBOTS-aa4150-33",
		"edition": 51,
		"rank": 649
	},{
		"identifier": "COMBOTS-aa4150-01ba",
		"edition": 442,
		"rank": 650
	},{
		"identifier": "COMBOTS-aa4150-7c",
		"edition": 124,
		"rank": 651
	},{
		"identifier": "COMBOTS-aa4150-03",
		"edition": 3,
		"rank": 652
	},{
		"identifier": "COMBOTS-aa4150-02f3",
		"edition": 755,
		"rank": 653
	},{
		"identifier": "COMBOTS-aa4150-02a1",
		"edition": 673,
		"rank": 654
	},{
		"identifier": "COMBOTS-aa4150-9f",
		"edition": 159,
		"rank": 655
	},{
		"identifier": "COMBOTS-aa4150-01b8",
		"edition": 440,
		"rank": 656
	},{
		"identifier": "COMBOTS-aa4150-016c",
		"edition": 364,
		"rank": 657
	},{
		"identifier": "COMBOTS-aa4150-03d4",
		"edition": 980,
		"rank": 658
	},{
		"identifier": "COMBOTS-aa4150-02c5",
		"edition": 709,
		"rank": 659
	},{
		"identifier": "COMBOTS-aa4150-0229",
		"edition": 553,
		"rank": 660
	},{
		"identifier": "COMBOTS-aa4150-01d4",
		"edition": 468,
		"rank": 661
	},{
		"identifier": "COMBOTS-aa4150-02",
		"edition": 2,
		"rank": 662
	},{
		"identifier": "COMBOTS-aa4150-02de",
		"edition": 734,
		"rank": 663
	},{
		"identifier": "COMBOTS-aa4150-0102",
		"edition": 258,
		"rank": 664
	},{
		"identifier": "COMBOTS-aa4150-020c",
		"edition": 524,
		"rank": 665
	},{
		"identifier": "COMBOTS-aa4150-01ef",
		"edition": 495,
		"rank": 666
	},{
		"identifier": "COMBOTS-aa4150-01a0",
		"edition": 416,
		"rank": 667
	},{
		"identifier": "COMBOTS-aa4150-0130",
		"edition": 304,
		"rank": 668
	},{
		"identifier": "COMBOTS-aa4150-0359",
		"edition": 857,
		"rank": 669
	},{
		"identifier": "COMBOTS-aa4150-01bc",
		"edition": 444,
		"rank": 670
	},{
		"identifier": "COMBOTS-aa4150-0347",
		"edition": 839,
		"rank": 671
	},{
		"identifier": "COMBOTS-aa4150-0157",
		"edition": 343,
		"rank": 672
	},{
		"identifier": "COMBOTS-aa4150-0105",
		"edition": 261,
		"rank": 673
	},{
		"identifier": "COMBOTS-aa4150-0372",
		"edition": 882,
		"rank": 674
	},{
		"identifier": "COMBOTS-aa4150-03d2",
		"edition": 978,
		"rank": 675
	},{
		"identifier": "COMBOTS-aa4150-b4",
		"edition": 180,
		"rank": 676
	},{
		"identifier": "COMBOTS-aa4150-0203",
		"edition": 515,
		"rank": 677
	},{
		"identifier": "COMBOTS-aa4150-86",
		"edition": 134,
		"rank": 678
	},{
		"identifier": "COMBOTS-aa4150-90",
		"edition": 144,
		"rank": 679
	},{
		"identifier": "COMBOTS-aa4150-0172",
		"edition": 370,
		"rank": 680
	},{
		"identifier": "COMBOTS-aa4150-0101",
		"edition": 257,
		"rank": 681
	},{
		"identifier": "COMBOTS-aa4150-032e",
		"edition": 814,
		"rank": 682
	},{
		"identifier": "COMBOTS-aa4150-039c",
		"edition": 924,
		"rank": 683
	},{
		"identifier": "COMBOTS-aa4150-01f3",
		"edition": 499,
		"rank": 684
	},{
		"identifier": "COMBOTS-aa4150-0154",
		"edition": 340,
		"rank": 685
	},{
		"identifier": "COMBOTS-aa4150-0295",
		"edition": 661,
		"rank": 686
	},{
		"identifier": "COMBOTS-aa4150-018b",
		"edition": 395,
		"rank": 687
	},{
		"identifier": "COMBOTS-aa4150-010e",
		"edition": 270,
		"rank": 688
	},{
		"identifier": "COMBOTS-aa4150-027a",
		"edition": 634,
		"rank": 689
	},{
		"identifier": "COMBOTS-aa4150-11",
		"edition": 17,
		"rank": 690
	},{
		"identifier": "COMBOTS-aa4150-021d",
		"edition": 541,
		"rank": 691
	},{
		"identifier": "COMBOTS-aa4150-0192",
		"edition": 402,
		"rank": 692
	},{
		"identifier": "COMBOTS-aa4150-01a6",
		"edition": 422,
		"rank": 693
	},{
		"identifier": "COMBOTS-aa4150-40",
		"edition": 64,
		"rank": 694
	},{
		"identifier": "COMBOTS-aa4150-0333",
		"edition": 819,
		"rank": 695
	},{
		"identifier": "COMBOTS-aa4150-0c",
		"edition": 12,
		"rank": 696
	},{
		"identifier": "COMBOTS-aa4150-0196",
		"edition": 406,
		"rank": 697
	},{
		"identifier": "COMBOTS-aa4150-025d",
		"edition": 605,
		"rank": 698
	},{
		"identifier": "COMBOTS-aa4150-0262",
		"edition": 610,
		"rank": 699
	},{
		"identifier": "COMBOTS-aa4150-0345",
		"edition": 837,
		"rank": 700
	},{
		"identifier": "COMBOTS-aa4150-02f0",
		"edition": 752,
		"rank": 701
	},{
		"identifier": "COMBOTS-aa4150-0284",
		"edition": 644,
		"rank": 702
	},{
		"identifier": "COMBOTS-aa4150-01b4",
		"edition": 436,
		"rank": 703
	},{
		"identifier": "COMBOTS-aa4150-01ed",
		"edition": 493,
		"rank": 704
	},{
		"identifier": "COMBOTS-aa4150-01c7",
		"edition": 455,
		"rank": 705
	},{
		"identifier": "COMBOTS-aa4150-036d",
		"edition": 877,
		"rank": 706
	},{
		"identifier": "COMBOTS-aa4150-05",
		"edition": 5,
		"rank": 707
	},{
		"identifier": "COMBOTS-aa4150-01a5",
		"edition": 421,
		"rank": 708
	},{
		"identifier": "COMBOTS-aa4150-030c",
		"edition": 780,
		"rank": 709
	},{
		"identifier": "COMBOTS-aa4150-0132",
		"edition": 306,
		"rank": 710
	},{
		"identifier": "COMBOTS-aa4150-28",
		"edition": 40,
		"rank": 711
	},{
		"identifier": "COMBOTS-aa4150-c2",
		"edition": 194,
		"rank": 712
	},{
		"identifier": "COMBOTS-aa4150-d5",
		"edition": 213,
		"rank": 713
	},{
		"identifier": "COMBOTS-aa4150-ff",
		"edition": 255,
		"rank": 714
	},{
		"identifier": "COMBOTS-aa4150-03cb",
		"edition": 971,
		"rank": 715
	},{
		"identifier": "COMBOTS-aa4150-01df",
		"edition": 479,
		"rank": 716
	},{
		"identifier": "COMBOTS-aa4150-024c",
		"edition": 588,
		"rank": 717
	},{
		"identifier": "COMBOTS-aa4150-03da",
		"edition": 986,
		"rank": 718
	},{
		"identifier": "COMBOTS-aa4150-01ca",
		"edition": 458,
		"rank": 719
	},{
		"identifier": "COMBOTS-aa4150-02f6",
		"edition": 758,
		"rank": 720
	},{
		"identifier": "COMBOTS-aa4150-01fc",
		"edition": 508,
		"rank": 721
	},{
		"identifier": "COMBOTS-aa4150-5e",
		"edition": 94,
		"rank": 722
	},{
		"identifier": "COMBOTS-aa4150-02a6",
		"edition": 678,
		"rank": 723
	},{
		"identifier": "COMBOTS-aa4150-0264",
		"edition": 612,
		"rank": 724
	},{
		"identifier": "COMBOTS-aa4150-0143",
		"edition": 323,
		"rank": 725
	},{
		"identifier": "COMBOTS-aa4150-037f",
		"edition": 895,
		"rank": 726
	},{
		"identifier": "COMBOTS-aa4150-0281",
		"edition": 641,
		"rank": 727
	},{
		"identifier": "COMBOTS-aa4150-ba",
		"edition": 186,
		"rank": 728
	},{
		"identifier": "COMBOTS-aa4150-0124",
		"edition": 292,
		"rank": 729
	},{
		"identifier": "COMBOTS-aa4150-03d7",
		"edition": 983,
		"rank": 730
	},{
		"identifier": "COMBOTS-aa4150-0325",
		"edition": 805,
		"rank": 731
	},{
		"identifier": "COMBOTS-aa4150-03a1",
		"edition": 929,
		"rank": 732
	},{
		"identifier": "COMBOTS-aa4150-f7",
		"edition": 247,
		"rank": 733
	},{
		"identifier": "COMBOTS-aa4150-0298",
		"edition": 664,
		"rank": 734
	},{
		"identifier": "COMBOTS-aa4150-0318",
		"edition": 792,
		"rank": 735
	},{
		"identifier": "COMBOTS-aa4150-0204",
		"edition": 516,
		"rank": 736
	},{
		"identifier": "COMBOTS-aa4150-033b",
		"edition": 827,
		"rank": 737
	},{
		"identifier": "COMBOTS-aa4150-017c",
		"edition": 380,
		"rank": 738
	},{
		"identifier": "COMBOTS-aa4150-0309",
		"edition": 777,
		"rank": 739
	},{
		"identifier": "COMBOTS-aa4150-039d",
		"edition": 925,
		"rank": 740
	},{
		"identifier": "COMBOTS-aa4150-0286",
		"edition": 646,
		"rank": 741
	},{
		"identifier": "COMBOTS-aa4150-f3",
		"edition": 243,
		"rank": 742
	},{
		"identifier": "COMBOTS-aa4150-01d6",
		"edition": 470,
		"rank": 743
	},{
		"identifier": "COMBOTS-aa4150-0156",
		"edition": 342,
		"rank": 744
	},{
		"identifier": "COMBOTS-aa4150-03b6",
		"edition": 950,
		"rank": 745
	},{
		"identifier": "COMBOTS-aa4150-0240",
		"edition": 576,
		"rank": 746
	},{
		"identifier": "COMBOTS-aa4150-03c4",
		"edition": 964,
		"rank": 747
	},{
		"identifier": "COMBOTS-aa4150-0195",
		"edition": 405,
		"rank": 748
	},{
		"identifier": "COMBOTS-aa4150-012d",
		"edition": 301,
		"rank": 749
	},{
		"identifier": "COMBOTS-aa4150-3e",
		"edition": 62,
		"rank": 750
	},{
		"identifier": "COMBOTS-aa4150-014c",
		"edition": 332,
		"rank": 751
	},{
		"identifier": "COMBOTS-aa4150-03cd",
		"edition": 973,
		"rank": 752
	},{
		"identifier": "COMBOTS-aa4150-3f",
		"edition": 63,
		"rank": 753
	},{
		"identifier": "COMBOTS-aa4150-01dd",
		"edition": 477,
		"rank": 754
	},{
		"identifier": "COMBOTS-aa4150-e8",
		"edition": 232,
		"rank": 755
	},{
		"identifier": "COMBOTS-aa4150-038b",
		"edition": 907,
		"rank": 756
	},{
		"identifier": "COMBOTS-aa4150-c8",
		"edition": 200,
		"rank": 757
	},{
		"identifier": "COMBOTS-aa4150-0194",
		"edition": 404,
		"rank": 758
	},{
		"identifier": "COMBOTS-aa4150-031c",
		"edition": 796,
		"rank": 759
	},{
		"identifier": "COMBOTS-aa4150-0323",
		"edition": 803,
		"rank": 760
	},{
		"identifier": "COMBOTS-aa4150-01ee",
		"edition": 494,
		"rank": 761
	},{
		"identifier": "COMBOTS-aa4150-02f9",
		"edition": 761,
		"rank": 762
	},{
		"identifier": "COMBOTS-aa4150-0141",
		"edition": 321,
		"rank": 763
	},{
		"identifier": "COMBOTS-aa4150-0257",
		"edition": 599,
		"rank": 764
	},{
		"identifier": "COMBOTS-aa4150-32",
		"edition": 50,
		"rank": 765
	},{
		"identifier": "COMBOTS-aa4150-036a",
		"edition": 874,
		"rank": 766
	},{
		"identifier": "COMBOTS-aa4150-01b0",
		"edition": 432,
		"rank": 767
	},{
		"identifier": "COMBOTS-aa4150-0177",
		"edition": 375,
		"rank": 768
	},{
		"identifier": "COMBOTS-aa4150-03cf",
		"edition": 975,
		"rank": 769
	},{
		"identifier": "COMBOTS-aa4150-7b",
		"edition": 123,
		"rank": 770
	},{
		"identifier": "COMBOTS-aa4150-03ca",
		"edition": 970,
		"rank": 771
	},{
		"identifier": "COMBOTS-aa4150-012e",
		"edition": 302,
		"rank": 772
	},{
		"identifier": "COMBOTS-aa4150-1a",
		"edition": 26,
		"rank": 773
	},{
		"identifier": "COMBOTS-aa4150-62",
		"edition": 98,
		"rank": 774
	},{
		"identifier": "COMBOTS-aa4150-0382",
		"edition": 898,
		"rank": 775
	},{
		"identifier": "COMBOTS-aa4150-18",
		"edition": 24,
		"rank": 776
	},{
		"identifier": "COMBOTS-aa4150-83",
		"edition": 131,
		"rank": 777
	},{
		"identifier": "COMBOTS-aa4150-44",
		"edition": 68,
		"rank": 778
	},{
		"identifier": "COMBOTS-aa4150-01a2",
		"edition": 418,
		"rank": 779
	},{
		"identifier": "COMBOTS-aa4150-0387",
		"edition": 903,
		"rank": 780
	},{
		"identifier": "COMBOTS-aa4150-038f",
		"edition": 911,
		"rank": 781
	},{
		"identifier": "COMBOTS-aa4150-2f",
		"edition": 47,
		"rank": 782
	},{
		"identifier": "COMBOTS-aa4150-38",
		"edition": 56,
		"rank": 783
	},{
		"identifier": "COMBOTS-aa4150-01",
		"edition": 1,
		"rank": 784
	},{
		"identifier": "COMBOTS-aa4150-025c",
		"edition": 604,
		"rank": 785
	},{
		"identifier": "COMBOTS-aa4150-0346",
		"edition": 838,
		"rank": 786
	},{
		"identifier": "COMBOTS-aa4150-0125",
		"edition": 293,
		"rank": 787
	},{
		"identifier": "COMBOTS-aa4150-0238",
		"edition": 568,
		"rank": 788
	},{
		"identifier": "COMBOTS-aa4150-03ba",
		"edition": 954,
		"rank": 789
	},{
		"identifier": "COMBOTS-aa4150-dd",
		"edition": 221,
		"rank": 790
	},{
		"identifier": "COMBOTS-aa4150-01c9",
		"edition": 457,
		"rank": 791
	},{
		"identifier": "COMBOTS-aa4150-0184",
		"edition": 388,
		"rank": 792
	},{
		"identifier": "COMBOTS-aa4150-0226",
		"edition": 550,
		"rank": 793
	},{
		"identifier": "COMBOTS-aa4150-028b",
		"edition": 651,
		"rank": 794
	},{
		"identifier": "COMBOTS-aa4150-01cb",
		"edition": 459,
		"rank": 795
	},{
		"identifier": "COMBOTS-aa4150-24",
		"edition": 36,
		"rank": 796
	},{
		"identifier": "COMBOTS-aa4150-0313",
		"edition": 787,
		"rank": 797
	},{
		"identifier": "COMBOTS-aa4150-0310",
		"edition": 784,
		"rank": 798
	},{
		"identifier": "COMBOTS-aa4150-87",
		"edition": 135,
		"rank": 799
	},{
		"identifier": "COMBOTS-aa4150-0183",
		"edition": 387,
		"rank": 800
	},{
		"identifier": "COMBOTS-aa4150-01a8",
		"edition": 424,
		"rank": 801
	},{
		"identifier": "COMBOTS-aa4150-12",
		"edition": 18,
		"rank": 802
	},{
		"identifier": "COMBOTS-aa4150-029b",
		"edition": 667,
		"rank": 803
	},{
		"identifier": "COMBOTS-aa4150-0126",
		"edition": 294,
		"rank": 804
	},{
		"identifier": "COMBOTS-aa4150-03dc",
		"edition": 988,
		"rank": 805
	},{
		"identifier": "COMBOTS-aa4150-0297",
		"edition": 663,
		"rank": 806
	},{
		"identifier": "COMBOTS-aa4150-02e0",
		"edition": 736,
		"rank": 807
	},{
		"identifier": "COMBOTS-aa4150-65",
		"edition": 101,
		"rank": 808
	},{
		"identifier": "COMBOTS-aa4150-02b4",
		"edition": 692,
		"rank": 809
	},{
		"identifier": "COMBOTS-aa4150-01b2",
		"edition": 434,
		"rank": 810
	},{
		"identifier": "COMBOTS-aa4150-020b",
		"edition": 523,
		"rank": 811
	},{
		"identifier": "COMBOTS-aa4150-03af",
		"edition": 943,
		"rank": 812
	},{
		"identifier": "COMBOTS-aa4150-c7",
		"edition": 199,
		"rank": 813
	},{
		"identifier": "COMBOTS-aa4150-0315",
		"edition": 789,
		"rank": 814
	},{
		"identifier": "COMBOTS-aa4150-032c",
		"edition": 812,
		"rank": 815
	},{
		"identifier": "COMBOTS-aa4150-0219",
		"edition": 537,
		"rank": 816
	},{
		"identifier": "COMBOTS-aa4150-a5",
		"edition": 165,
		"rank": 817
	},{
		"identifier": "COMBOTS-aa4150-02ee",
		"edition": 750,
		"rank": 818
	},{
		"identifier": "COMBOTS-aa4150-0361",
		"edition": 865,
		"rank": 819
	},{
		"identifier": "COMBOTS-aa4150-02ba",
		"edition": 698,
		"rank": 820
	},{
		"identifier": "COMBOTS-aa4150-0113",
		"edition": 275,
		"rank": 821
	},{
		"identifier": "COMBOTS-aa4150-55",
		"edition": 85,
		"rank": 822
	},{
		"identifier": "COMBOTS-aa4150-016f",
		"edition": 367,
		"rank": 823
	},{
		"identifier": "COMBOTS-aa4150-03b7",
		"edition": 951,
		"rank": 824
	},{
		"identifier": "COMBOTS-aa4150-02ae",
		"edition": 686,
		"rank": 825
	},{
		"identifier": "COMBOTS-aa4150-01f7",
		"edition": 503,
		"rank": 826
	},{
		"identifier": "COMBOTS-aa4150-02d5",
		"edition": 725,
		"rank": 827
	},{
		"identifier": "COMBOTS-aa4150-0290",
		"edition": 656,
		"rank": 828
	},{
		"identifier": "COMBOTS-aa4150-7a",
		"edition": 122,
		"rank": 829
	},{
		"identifier": "COMBOTS-aa4150-f6",
		"edition": 246,
		"rank": 830
	},{
		"identifier": "COMBOTS-aa4150-67",
		"edition": 103,
		"rank": 831
	},{
		"identifier": "COMBOTS-aa4150-0107",
		"edition": 263,
		"rank": 832
	},{
		"identifier": "COMBOTS-aa4150-0357",
		"edition": 855,
		"rank": 833
	},{
		"identifier": "COMBOTS-aa4150-031b",
		"edition": 795,
		"rank": 834
	},{
		"identifier": "COMBOTS-aa4150-77",
		"edition": 119,
		"rank": 835
	},{
		"identifier": "COMBOTS-aa4150-02f1",
		"edition": 753,
		"rank": 836
	},{
		"identifier": "COMBOTS-aa4150-61",
		"edition": 97,
		"rank": 837
	},{
		"identifier": "COMBOTS-aa4150-0306",
		"edition": 774,
		"rank": 838
	},{
		"identifier": "COMBOTS-aa4150-0379",
		"edition": 889,
		"rank": 839
	},{
		"identifier": "COMBOTS-aa4150-01fe",
		"edition": 510,
		"rank": 840
	},{
		"identifier": "COMBOTS-aa4150-af",
		"edition": 175,
		"rank": 841
	},{
		"identifier": "COMBOTS-aa4150-fc",
		"edition": 252,
		"rank": 842
	},{
		"identifier": "COMBOTS-aa4150-c3",
		"edition": 195,
		"rank": 843
	},{
		"identifier": "COMBOTS-aa4150-034f",
		"edition": 847,
		"rank": 844
	},{
		"identifier": "COMBOTS-aa4150-84",
		"edition": 132,
		"rank": 845
	},{
		"identifier": "COMBOTS-aa4150-037e",
		"edition": 894,
		"rank": 846
	},{
		"identifier": "COMBOTS-aa4150-01e0",
		"edition": 480,
		"rank": 847
	},{
		"identifier": "COMBOTS-aa4150-035c",
		"edition": 860,
		"rank": 848
	},{
		"identifier": "COMBOTS-aa4150-033d",
		"edition": 829,
		"rank": 849
	},{
		"identifier": "COMBOTS-aa4150-016d",
		"edition": 365,
		"rank": 850
	},{
		"identifier": "COMBOTS-aa4150-0111",
		"edition": 273,
		"rank": 851
	},{
		"identifier": "COMBOTS-aa4150-01e2",
		"edition": 482,
		"rank": 852
	},{
		"identifier": "COMBOTS-aa4150-0294",
		"edition": 660,
		"rank": 853
	},{
		"identifier": "COMBOTS-aa4150-49",
		"edition": 73,
		"rank": 854
	},{
		"identifier": "COMBOTS-aa4150-16",
		"edition": 22,
		"rank": 855
	},{
		"identifier": "COMBOTS-aa4150-03d3",
		"edition": 979,
		"rank": 856
	},{
		"identifier": "COMBOTS-aa4150-0171",
		"edition": 369,
		"rank": 857
	},{
		"identifier": "COMBOTS-aa4150-01cc",
		"edition": 460,
		"rank": 858
	},{
		"identifier": "COMBOTS-aa4150-e5",
		"edition": 229,
		"rank": 859
	},{
		"identifier": "COMBOTS-aa4150-0370",
		"edition": 880,
		"rank": 860
	},{
		"identifier": "COMBOTS-aa4150-03bb",
		"edition": 955,
		"rank": 861
	},{
		"identifier": "COMBOTS-aa4150-20",
		"edition": 32,
		"rank": 862
	},{
		"identifier": "COMBOTS-aa4150-d7",
		"edition": 215,
		"rank": 863
	},{
		"identifier": "COMBOTS-aa4150-03a8",
		"edition": 936,
		"rank": 864
	},{
		"identifier": "COMBOTS-aa4150-a6",
		"edition": 166,
		"rank": 865
	},{
		"identifier": "COMBOTS-aa4150-fd",
		"edition": 253,
		"rank": 866
	},{
		"identifier": "COMBOTS-aa4150-0211",
		"edition": 529,
		"rank": 867
	},{
		"identifier": "COMBOTS-aa4150-03aa",
		"edition": 938,
		"rank": 868
	},{
		"identifier": "COMBOTS-aa4150-ca",
		"edition": 202,
		"rank": 869
	},{
		"identifier": "COMBOTS-aa4150-01f4",
		"edition": 500,
		"rank": 870
	},{
		"identifier": "COMBOTS-aa4150-01c5",
		"edition": 453,
		"rank": 871
	},{
		"identifier": "COMBOTS-aa4150-029e",
		"edition": 670,
		"rank": 872
	},{
		"identifier": "COMBOTS-aa4150-0270",
		"edition": 624,
		"rank": 873
	},{
		"identifier": "COMBOTS-aa4150-17",
		"edition": 23,
		"rank": 874
	},{
		"identifier": "COMBOTS-aa4150-015c",
		"edition": 348,
		"rank": 875
	},{
		"identifier": "COMBOTS-aa4150-0388",
		"edition": 904,
		"rank": 876
	},{
		"identifier": "COMBOTS-aa4150-4d",
		"edition": 77,
		"rank": 877
	},{
		"identifier": "COMBOTS-aa4150-031a",
		"edition": 794,
		"rank": 878
	},{
		"identifier": "COMBOTS-aa4150-0231",
		"edition": 561,
		"rank": 879
	},{
		"identifier": "COMBOTS-aa4150-023f",
		"edition": 575,
		"rank": 880
	},{
		"identifier": "COMBOTS-aa4150-b9",
		"edition": 185,
		"rank": 881
	},{
		"identifier": "COMBOTS-aa4150-57",
		"edition": 87,
		"rank": 882
	},{
		"identifier": "COMBOTS-aa4150-99",
		"edition": 153,
		"rank": 883
	},{
		"identifier": "COMBOTS-aa4150-13",
		"edition": 19,
		"rank": 884
	},{
		"identifier": "COMBOTS-aa4150-71",
		"edition": 113,
		"rank": 885
	},{
		"identifier": "COMBOTS-aa4150-02b7",
		"edition": 695,
		"rank": 886
	},{
		"identifier": "COMBOTS-aa4150-0365",
		"edition": 869,
		"rank": 887
	},{
		"identifier": "COMBOTS-aa4150-0301",
		"edition": 769,
		"rank": 888
	},{
		"identifier": "COMBOTS-aa4150-f0",
		"edition": 240,
		"rank": 889
	},{
		"identifier": "COMBOTS-aa4150-02db",
		"edition": 731,
		"rank": 890
	},{
		"identifier": "COMBOTS-aa4150-02c4",
		"edition": 708,
		"rank": 891
	},{
		"identifier": "COMBOTS-aa4150-02d0",
		"edition": 720,
		"rank": 892
	},{
		"identifier": "COMBOTS-aa4150-02fb",
		"edition": 763,
		"rank": 893
	},{
		"identifier": "COMBOTS-aa4150-0287",
		"edition": 647,
		"rank": 894
	},{
		"identifier": "COMBOTS-aa4150-0261",
		"edition": 609,
		"rank": 895
	},{
		"identifier": "COMBOTS-aa4150-92",
		"edition": 146,
		"rank": 896
	},{
		"identifier": "COMBOTS-aa4150-0118",
		"edition": 280,
		"rank": 897
	},{
		"identifier": "COMBOTS-aa4150-27",
		"edition": 39,
		"rank": 898
	},{
		"identifier": "COMBOTS-aa4150-01bb",
		"edition": 443,
		"rank": 899
	},{
		"identifier": "COMBOTS-aa4150-03c6",
		"edition": 966,
		"rank": 900
	},{
		"identifier": "COMBOTS-aa4150-01f8",
		"edition": 504,
		"rank": 901
	},{
		"identifier": "COMBOTS-aa4150-0396",
		"edition": 918,
		"rank": 902
	},{
		"identifier": "COMBOTS-aa4150-02a7",
		"edition": 679,
		"rank": 903
	},{
		"identifier": "COMBOTS-aa4150-be",
		"edition": 190,
		"rank": 904
	},{
		"identifier": "COMBOTS-aa4150-02a4",
		"edition": 676,
		"rank": 905
	},{
		"identifier": "COMBOTS-aa4150-0221",
		"edition": 545,
		"rank": 906
	},{
		"identifier": "COMBOTS-aa4150-035a",
		"edition": 858,
		"rank": 907
	},{
		"identifier": "COMBOTS-aa4150-64",
		"edition": 100,
		"rank": 908
	},{
		"identifier": "COMBOTS-aa4150-0119",
		"edition": 281,
		"rank": 909
	},{
		"identifier": "COMBOTS-aa4150-0305",
		"edition": 773,
		"rank": 910
	},{
		"identifier": "COMBOTS-aa4150-0258",
		"edition": 600,
		"rank": 911
	},{
		"identifier": "COMBOTS-aa4150-013c",
		"edition": 316,
		"rank": 912
	},{
		"identifier": "COMBOTS-aa4150-01de",
		"edition": 478,
		"rank": 913
	},{
		"identifier": "COMBOTS-aa4150-ad",
		"edition": 173,
		"rank": 914
	},{
		"identifier": "COMBOTS-aa4150-c1",
		"edition": 193,
		"rank": 915
	},{
		"identifier": "COMBOTS-aa4150-01e8",
		"edition": 488,
		"rank": 916
	},{
		"identifier": "COMBOTS-aa4150-02ec",
		"edition": 748,
		"rank": 917
	},{
		"identifier": "COMBOTS-aa4150-03bf",
		"edition": 959,
		"rank": 918
	},{
		"identifier": "COMBOTS-aa4150-c9",
		"edition": 201,
		"rank": 919
	},{
		"identifier": "COMBOTS-aa4150-0335",
		"edition": 821,
		"rank": 920
	},{
		"identifier": "COMBOTS-aa4150-0360",
		"edition": 864,
		"rank": 921
	},{
		"identifier": "COMBOTS-aa4150-019d",
		"edition": 413,
		"rank": 922
	},{
		"identifier": "COMBOTS-aa4150-0242",
		"edition": 578,
		"rank": 923
	},{
		"identifier": "COMBOTS-aa4150-022e",
		"edition": 558,
		"rank": 924
	},{
		"identifier": "COMBOTS-aa4150-025e",
		"edition": 606,
		"rank": 925
	},{
		"identifier": "COMBOTS-aa4150-013f",
		"edition": 319,
		"rank": 926
	},{
		"identifier": "COMBOTS-aa4150-ce",
		"edition": 206,
		"rank": 927
	},{
		"identifier": "COMBOTS-aa4150-95",
		"edition": 149,
		"rank": 928
	},{
		"identifier": "COMBOTS-aa4150-02a9",
		"edition": 681,
		"rank": 929
	},{
		"identifier": "COMBOTS-aa4150-7f",
		"edition": 127,
		"rank": 930
	},{
		"identifier": "COMBOTS-aa4150-013d",
		"edition": 317,
		"rank": 931
	},{
		"identifier": "COMBOTS-aa4150-01e5",
		"edition": 485,
		"rank": 932
	},{
		"identifier": "COMBOTS-aa4150-01be",
		"edition": 446,
		"rank": 933
	},{
		"identifier": "COMBOTS-aa4150-0210",
		"edition": 528,
		"rank": 934
	},{
		"identifier": "COMBOTS-aa4150-032f",
		"edition": 815,
		"rank": 935
	},{
		"identifier": "COMBOTS-aa4150-0340",
		"edition": 832,
		"rank": 936
	},{
		"identifier": "COMBOTS-aa4150-2e",
		"edition": 46,
		"rank": 937
	},{
		"identifier": "COMBOTS-aa4150-03c1",
		"edition": 961,
		"rank": 938
	},{
		"identifier": "COMBOTS-aa4150-026c",
		"edition": 620,
		"rank": 939
	},{
		"identifier": "COMBOTS-aa4150-02e6",
		"edition": 742,
		"rank": 940
	},{
		"identifier": "COMBOTS-aa4150-0353",
		"edition": 851,
		"rank": 941
	},{
		"identifier": "COMBOTS-aa4150-031d",
		"edition": 797,
		"rank": 942
	},{
		"identifier": "COMBOTS-aa4150-0137",
		"edition": 311,
		"rank": 943
	},{
		"identifier": "COMBOTS-aa4150-a2",
		"edition": 162,
		"rank": 944
	},{
		"identifier": "COMBOTS-aa4150-01c3",
		"edition": 451,
		"rank": 945
	},{
		"identifier": "COMBOTS-aa4150-01e6",
		"edition": 486,
		"rank": 946
	},{
		"identifier": "COMBOTS-aa4150-038d",
		"edition": 909,
		"rank": 947
	},{
		"identifier": "COMBOTS-aa4150-01c0",
		"edition": 448,
		"rank": 948
	},{
		"identifier": "COMBOTS-aa4150-02e7",
		"edition": 743,
		"rank": 949
	},{
		"identifier": "COMBOTS-aa4150-02a3",
		"edition": 675,
		"rank": 950
	},{
		"identifier": "COMBOTS-aa4150-01b9",
		"edition": 441,
		"rank": 951
	},{
		"identifier": "COMBOTS-aa4150-02fc",
		"edition": 764,
		"rank": 952
	},{
		"identifier": "COMBOTS-aa4150-0170",
		"edition": 368,
		"rank": 953
	},{
		"identifier": "COMBOTS-aa4150-0114",
		"edition": 276,
		"rank": 954
	},{
		"identifier": "COMBOTS-aa4150-2c",
		"edition": 44,
		"rank": 955
	},{
		"identifier": "COMBOTS-aa4150-01b1",
		"edition": 433,
		"rank": 956
	},{
		"identifier": "COMBOTS-aa4150-01db",
		"edition": 475,
		"rank": 957
	},{
		"identifier": "COMBOTS-aa4150-0199",
		"edition": 409,
		"rank": 958
	},{
		"identifier": "COMBOTS-aa4150-021f",
		"edition": 543,
		"rank": 959
	},{
		"identifier": "COMBOTS-aa4150-01ae",
		"edition": 430,
		"rank": 960
	},{
		"identifier": "COMBOTS-aa4150-0e",
		"edition": 14,
		"rank": 961
	},{
		"identifier": "COMBOTS-aa4150-bb",
		"edition": 187,
		"rank": 962
	},{
		"identifier": "COMBOTS-aa4150-0267",
		"edition": 615,
		"rank": 963
	},{
		"identifier": "COMBOTS-aa4150-06",
		"edition": 6,
		"rank": 964
	},{
		"identifier": "COMBOTS-aa4150-02ab",
		"edition": 683,
		"rank": 965
	},{
		"identifier": "COMBOTS-aa4150-02cf",
		"edition": 719,
		"rank": 966
	},{
		"identifier": "COMBOTS-aa4150-0147",
		"edition": 327,
		"rank": 967
	},{
		"identifier": "COMBOTS-aa4150-03d5",
		"edition": 981,
		"rank": 968
	},{
		"identifier": "COMBOTS-aa4150-0265",
		"edition": 613,
		"rank": 969
	},{
		"identifier": "COMBOTS-aa4150-53",
		"edition": 83,
		"rank": 970
	},{
		"identifier": "COMBOTS-aa4150-03c7",
		"edition": 967,
		"rank": 971
	},{
		"identifier": "COMBOTS-aa4150-0179",
		"edition": 377,
		"rank": 972
	},{
		"identifier": "COMBOTS-aa4150-014e",
		"edition": 334,
		"rank": 973
	},{
		"identifier": "COMBOTS-aa4150-88",
		"edition": 136,
		"rank": 974
	},{
		"identifier": "COMBOTS-aa4150-29",
		"edition": 41,
		"rank": 975
	},{
		"identifier": "COMBOTS-aa4150-0278",
		"edition": 632,
		"rank": 976
	},{
		"identifier": "COMBOTS-aa4150-02a5",
		"edition": 677,
		"rank": 977
	},{
		"identifier": "COMBOTS-aa4150-0200",
		"edition": 512,
		"rank": 978
	},{
		"identifier": "COMBOTS-aa4150-0331",
		"edition": 817,
		"rank": 979
	},{
		"identifier": "COMBOTS-aa4150-03cc",
		"edition": 972,
		"rank": 980
	},{
		"identifier": "COMBOTS-aa4150-b7",
		"edition": 183,
		"rank": 981
	},{
		"identifier": "COMBOTS-aa4150-cd",
		"edition": 205,
		"rank": 982
	},{
		"identifier": "COMBOTS-aa4150-030a",
		"edition": 778,
		"rank": 983
	},{
		"identifier": "COMBOTS-aa4150-01cf",
		"edition": 463,
		"rank": 984
	},{
		"identifier": "COMBOTS-aa4150-0329",
		"edition": 809,
		"rank": 985
	},{
		"identifier": "COMBOTS-aa4150-010d",
		"edition": 269,
		"rank": 986
	},{
		"identifier": "COMBOTS-aa4150-023e",
		"edition": 574,
		"rank": 987
	},{
		"identifier": "COMBOTS-aa4150-011c",
		"edition": 284,
		"rank": 988
	},{
		"identifier": "COMBOTS-aa4150-10",
		"edition": 16,
		"rank": 989
	},{
		"identifier": "COMBOTS-aa4150-0296",
		"edition": 662,
		"rank": 990
	},{
		"identifier": "COMBOTS-aa4150-026f",
		"edition": 623,
		"rank": 991
	},{
		"identifier": "COMBOTS-aa4150-0322",
		"edition": 802,
		"rank": 992
	},{
		"identifier": "COMBOTS-aa4150-01d5",
		"edition": 469,
		"rank": 993
	},{
		"identifier": "COMBOTS-aa4150-0254",
		"edition": 596,
		"rank": 994
	},{
		"identifier": "COMBOTS-aa4150-0128",
		"edition": 296,
		"rank": 995
	},{
		"identifier": "COMBOTS-aa4150-01a7",
		"edition": 423,
		"rank": 996
	},{
		"identifier": "COMBOTS-aa4150-03d1",
		"edition": 977,
		"rank": 997
	},{
		"identifier": "COMBOTS-aa4150-0377",
		"edition": 887,
		"rank": 998
	},{
		"identifier": "COMBOTS-aa4150-0373",
		"edition": 883,
		"rank": 999
	}
]